{
"meta":{"test_sets":[],"test_metrics":[],"learn_metrics":[{"best_value":"Min","name":"RMSE"}],"launch_mode":"Train","parameters":"","iteration_count":1000,"learn_sets":["learn"],"name":"experiment"},
"iterations":[
{"learn":[14.61268541],"iteration":0,"passed_time":0.1371572577,"remaining_time":137.0201004},
{"learn":[14.23196558],"iteration":1,"passed_time":0.1408586858,"remaining_time":70.28848422},
{"learn":[13.86674177],"iteration":2,"passed_time":0.1442399011,"remaining_time":47.93572713},
{"learn":[13.49946468],"iteration":3,"passed_time":0.1479736236,"remaining_time":36.84543227},
{"learn":[13.16661202],"iteration":4,"passed_time":0.1517573432,"remaining_time":30.19971129},
{"learn":[12.85632158],"iteration":5,"passed_time":0.1550824957,"remaining_time":25.69200012},
{"learn":[12.56784336],"iteration":6,"passed_time":0.1584615736,"remaining_time":22.47890609},
{"learn":[12.31617801],"iteration":7,"passed_time":0.1618751345,"remaining_time":20.07251667},
{"learn":[12.01509946],"iteration":8,"passed_time":0.1653063304,"remaining_time":18.20206371},
{"learn":[11.71512571],"iteration":9,"passed_time":0.1685745338,"remaining_time":16.68887885},
{"learn":[11.43264457],"iteration":10,"passed_time":0.1721564392,"remaining_time":15.47842894},
{"learn":[11.17973129],"iteration":11,"passed_time":0.1757962859,"remaining_time":14.4738942},
{"learn":[10.93746433],"iteration":12,"passed_time":0.1781554096,"remaining_time":13.52610687},
{"learn":[10.69387075],"iteration":13,"passed_time":0.1803961635,"remaining_time":12.70504408},
{"learn":[10.4615922],"iteration":14,"passed_time":0.1825390178,"remaining_time":11.98672883},
{"learn":[10.2299235],"iteration":15,"passed_time":0.1842281934,"remaining_time":11.3300339},
{"learn":[10.01419731],"iteration":16,"passed_time":0.1859311732,"remaining_time":10.75119666},
{"learn":[9.795856918],"iteration":17,"passed_time":0.1876687191,"remaining_time":10.23837123},
{"learn":[9.60040151],"iteration":18,"passed_time":0.1891333226,"remaining_time":9.765252077},
{"learn":[9.418664989],"iteration":19,"passed_time":0.1905253116,"remaining_time":9.335740268},
{"learn":[9.249278645],"iteration":20,"passed_time":0.1918895136,"remaining_time":8.945706372},
{"learn":[9.090113396],"iteration":21,"passed_time":0.193261435,"remaining_time":8.591349246},
{"learn":[8.909548708],"iteration":22,"passed_time":0.1945937099,"remaining_time":8.266002372},
{"learn":[8.740140208],"iteration":23,"passed_time":0.195708737,"remaining_time":7.95882197},
{"learn":[8.59377682],"iteration":24,"passed_time":0.1968276142,"remaining_time":7.676276954},
{"learn":[8.453885414],"iteration":25,"passed_time":0.1979286063,"remaining_time":7.414710097},
{"learn":[8.317732234],"iteration":26,"passed_time":0.1990428173,"remaining_time":7.17291338},
{"learn":[8.180896085],"iteration":27,"passed_time":0.2002492364,"remaining_time":6.951509208},
{"learn":[8.053220863],"iteration":28,"passed_time":0.2012159554,"remaining_time":6.737265264},
{"learn":[7.924234474],"iteration":29,"passed_time":0.2021679587,"remaining_time":6.536763997},
{"learn":[7.818879511],"iteration":30,"passed_time":0.2030897243,"remaining_time":6.348191704},
{"learn":[7.719346395],"iteration":31,"passed_time":0.2040198525,"remaining_time":6.171600539},
{"learn":[7.624163594],"iteration":32,"passed_time":0.2049895648,"remaining_time":6.006815428},
{"learn":[7.524952543],"iteration":33,"passed_time":0.2059476736,"remaining_time":5.851336844},
{"learn":[7.424464745],"iteration":34,"passed_time":0.20688549,"remaining_time":5.70412851},
{"learn":[7.327482321],"iteration":35,"passed_time":0.2077460657,"remaining_time":5.562977981},
{"learn":[7.238666841],"iteration":36,"passed_time":0.2085537247,"remaining_time":5.42803343},
{"learn":[7.158842395],"iteration":37,"passed_time":0.2094268179,"remaining_time":5.301805233},
{"learn":[7.074348246],"iteration":38,"passed_time":0.2102487342,"remaining_time":5.18074445},
{"learn":[6.992269093],"iteration":39,"passed_time":0.2110570738,"remaining_time":5.065369772},
{"learn":[6.925219745],"iteration":40,"passed_time":0.2118870706,"remaining_time":4.956090262},
{"learn":[6.86013671],"iteration":41,"passed_time":0.2127144283,"remaining_time":4.851914817},
{"learn":[6.786739622],"iteration":42,"passed_time":0.2135081543,"remaining_time":4.751797761},
{"learn":[6.73057926],"iteration":43,"passed_time":0.2142459682,"remaining_time":4.654980583},
{"learn":[6.666356486],"iteration":44,"passed_time":0.2149785126,"remaining_time":4.562321768},
{"learn":[6.606182832],"iteration":45,"passed_time":0.2157370122,"remaining_time":4.474198036},
{"learn":[6.547854615],"iteration":46,"passed_time":0.2164498328,"remaining_time":4.388865758},
{"learn":[6.49240675],"iteration":47,"passed_time":0.2171806487,"remaining_time":4.307416199},
{"learn":[6.431317261],"iteration":48,"passed_time":0.2179027825,"remaining_time":4.229092778},
{"learn":[6.377586395],"iteration":49,"passed_time":0.2186589225,"remaining_time":4.154519528},
{"learn":[6.327558015],"iteration":50,"passed_time":0.219329382,"remaining_time":4.081246735},
{"learn":[6.282040317],"iteration":51,"passed_time":0.2200104256,"remaining_time":4.010959297},
{"learn":[6.237655841],"iteration":52,"passed_time":0.2206723973,"remaining_time":3.942957741},
{"learn":[6.192792003],"iteration":53,"passed_time":0.2213625485,"remaining_time":3.877943905},
{"learn":[6.150579347],"iteration":54,"passed_time":0.2220443152,"remaining_time":3.815125053},
{"learn":[6.115693845],"iteration":55,"passed_time":0.2227221598,"remaining_time":3.754459266},
{"learn":[6.078780782],"iteration":56,"passed_time":0.2233952748,"remaining_time":3.695820073},
{"learn":[6.045146957],"iteration":57,"passed_time":0.2240784558,"remaining_time":3.639343196},
{"learn":[6.008080327],"iteration":58,"passed_time":0.2247605802,"remaining_time":3.58474078},
{"learn":[5.977575734],"iteration":59,"passed_time":0.225388024,"remaining_time":3.531079042},
{"learn":[5.948036502],"iteration":60,"passed_time":0.2260084168,"remaining_time":3.479047596},
{"learn":[5.914888282],"iteration":61,"passed_time":0.2266831292,"remaining_time":3.429496374},
{"learn":[5.884957796],"iteration":62,"passed_time":0.227456647,"remaining_time":3.382966321},
{"learn":[5.849539885],"iteration":63,"passed_time":0.228133955,"remaining_time":3.336459092},
{"learn":[5.821387627],"iteration":64,"passed_time":0.228768652,"remaining_time":3.290749071},
{"learn":[5.797012279],"iteration":65,"passed_time":0.2294144297,"remaining_time":3.246561778},
{"learn":[5.768685095],"iteration":66,"passed_time":0.2300543849,"remaining_time":3.203593151},
{"learn":[5.755484587],"iteration":67,"passed_time":0.230420348,"remaining_time":3.158114182},
{"learn":[5.731887055],"iteration":68,"passed_time":0.2310611245,"remaining_time":3.117650824},
{"learn":[5.707148487],"iteration":69,"passed_time":0.2316941112,"remaining_time":3.078221763},
{"learn":[5.685365039],"iteration":70,"passed_time":0.2323496006,"remaining_time":3.040179986},
{"learn":[5.663541834],"iteration":71,"passed_time":0.2330132296,"remaining_time":3.003281627},
{"learn":[5.638108797],"iteration":72,"passed_time":0.2336351252,"remaining_time":2.966846042},
{"learn":[5.619204893],"iteration":73,"passed_time":0.2342644988,"remaining_time":2.931471971},
{"learn":[5.598472793],"iteration":74,"passed_time":0.2349311055,"remaining_time":2.897483634},
{"learn":[5.577007075],"iteration":75,"passed_time":0.2355505355,"remaining_time":2.863798616},
{"learn":[5.562637084],"iteration":76,"passed_time":0.2361805602,"remaining_time":2.831099443},
{"learn":[5.54729991],"iteration":77,"passed_time":0.2367904487,"remaining_time":2.798984535},
{"learn":[5.530737623],"iteration":78,"passed_time":0.237412478,"remaining_time":2.767808762},
{"learn":[5.513704873],"iteration":79,"passed_time":0.2380404912,"remaining_time":2.737465649},
{"learn":[5.501575529],"iteration":80,"passed_time":0.2386533773,"remaining_time":2.707684614},
{"learn":[5.484080734],"iteration":81,"passed_time":0.239300887,"remaining_time":2.679002612},
{"learn":[5.472178894],"iteration":82,"passed_time":0.2399588792,"remaining_time":2.651111955},
{"learn":[5.458923342],"iteration":83,"passed_time":0.2406720097,"remaining_time":2.624470962},
{"learn":[5.451382371],"iteration":84,"passed_time":0.2411224493,"remaining_time":2.595612249},
{"learn":[5.441410748],"iteration":85,"passed_time":0.2417994622,"remaining_time":2.569822192},
{"learn":[5.434047468],"iteration":86,"passed_time":0.2422604661,"remaining_time":2.542342593},
{"learn":[5.422107497],"iteration":87,"passed_time":0.242912819,"remaining_time":2.517460125},
{"learn":[5.40731265],"iteration":88,"passed_time":0.243580464,"remaining_time":2.493278682},
{"learn":[5.396360181],"iteration":89,"passed_time":0.2442238049,"remaining_time":2.469374027},
{"learn":[5.383793239],"iteration":90,"passed_time":0.2448671171,"remaining_time":2.445980324},
{"learn":[5.369605034],"iteration":91,"passed_time":0.2455273813,"remaining_time":2.423248502},
{"learn":[5.357467333],"iteration":92,"passed_time":0.2462498254,"remaining_time":2.40159776},
{"learn":[5.341109968],"iteration":93,"passed_time":0.2469226635,"remaining_time":2.379914182},
{"learn":[5.330529276],"iteration":94,"passed_time":0.2475675722,"remaining_time":2.358406872},
{"learn":[5.319862075],"iteration":95,"passed_time":0.2482195353,"remaining_time":2.337400624},
{"learn":[5.313052243],"iteration":96,"passed_time":0.2488504334,"remaining_time":2.316617952},
{"learn":[5.299677207],"iteration":97,"passed_time":0.24948953,"remaining_time":2.296322},
{"learn":[5.287546698],"iteration":98,"passed_time":0.2501175519,"remaining_time":2.276322366},
{"learn":[5.279803754],"iteration":99,"passed_time":0.2507500004,"remaining_time":2.256750004},
{"learn":[5.272254612],"iteration":100,"passed_time":0.2513891257,"remaining_time":2.237612118},
{"learn":[5.268813888],"iteration":101,"passed_time":0.2517586941,"remaining_time":2.216463797},
{"learn":[5.258113767],"iteration":102,"passed_time":0.2524072412,"remaining_time":2.198148498},
{"learn":[5.251018576],"iteration":103,"passed_time":0.2530459567,"remaining_time":2.180088242},
{"learn":[5.24171237],"iteration":104,"passed_time":0.2536773921,"remaining_time":2.16229777},
{"learn":[5.233984943],"iteration":105,"passed_time":0.2542941266,"remaining_time":2.144707068},
{"learn":[5.226240449],"iteration":106,"passed_time":0.254911046,"remaining_time":2.127435179},
{"learn":[5.220541644],"iteration":107,"passed_time":0.2555436647,"remaining_time":2.110601379},
{"learn":[5.211712096],"iteration":108,"passed_time":0.2561923541,"remaining_time":2.094196216},
{"learn":[5.203388597],"iteration":109,"passed_time":0.2568427251,"remaining_time":2.078091139},
{"learn":[5.196026544],"iteration":110,"passed_time":0.2575046065,"remaining_time":2.062356714},
{"learn":[5.188716772],"iteration":111,"passed_time":0.2581430842,"remaining_time":2.046705882},
{"learn":[5.182163132],"iteration":112,"passed_time":0.2587842148,"remaining_time":2.03134158},
{"learn":[5.17764747],"iteration":113,"passed_time":0.2594002679,"remaining_time":2.016040678},
{"learn":[5.170548056],"iteration":114,"passed_time":0.2600372532,"remaining_time":2.001156253},
{"learn":[5.165901827],"iteration":115,"passed_time":0.2605746401,"remaining_time":1.985758464},
{"learn":[5.160333668],"iteration":116,"passed_time":0.2612385998,"remaining_time":1.971569946},
{"learn":[5.148953243],"iteration":117,"passed_time":0.2618793798,"remaining_time":1.957437398},
{"learn":[5.144729126],"iteration":118,"passed_time":0.2623934279,"remaining_time":1.942593361},
{"learn":[5.139939946],"iteration":119,"passed_time":0.2631102939,"remaining_time":1.929475489},
{"learn":[5.132898872],"iteration":120,"passed_time":0.2638022681,"remaining_time":1.916381766},
{"learn":[5.129073077],"iteration":121,"passed_time":0.2644682966,"remaining_time":1.903304627},
{"learn":[5.127123916],"iteration":122,"passed_time":0.264814759,"remaining_time":1.888150762},
{"learn":[5.121282057],"iteration":123,"passed_time":0.2654907076,"remaining_time":1.875563386},
{"learn":[5.114489821],"iteration":124,"passed_time":0.2661838746,"remaining_time":1.863287123},
{"learn":[5.107777291],"iteration":125,"passed_time":0.2668641309,"remaining_time":1.851105162},
{"learn":[5.103518754],"iteration":126,"passed_time":0.2675572988,"remaining_time":1.839193085},
{"learn":[5.101133351],"iteration":127,"passed_time":0.2679861594,"remaining_time":1.825655711},
{"learn":[5.096462705],"iteration":128,"passed_time":0.2686753643,"remaining_time":1.814079398},
{"learn":[5.08562082],"iteration":129,"passed_time":0.2693588986,"remaining_time":1.802632629},
{"learn":[5.080483682],"iteration":130,"passed_time":0.2700797198,"remaining_time":1.79159753},
{"learn":[5.07437499],"iteration":131,"passed_time":0.2707540449,"remaining_time":1.780412962},
{"learn":[5.070683732],"iteration":132,"passed_time":0.2714305543,"remaining_time":1.769400681},
{"learn":[5.06432037],"iteration":133,"passed_time":0.2721065689,"remaining_time":1.758539468},
{"learn":[5.057436484],"iteration":134,"passed_time":0.2727794131,"remaining_time":1.747808832},
{"learn":[5.053254656],"iteration":135,"passed_time":0.2734765396,"remaining_time":1.737380369},
{"learn":[5.04801663],"iteration":136,"passed_time":0.2741565858,"remaining_time":1.726986376},
{"learn":[5.045680836],"iteration":137,"passed_time":0.2747425148,"remaining_time":1.716145274},
{"learn":[5.041857933],"iteration":138,"passed_time":0.2753953626,"remaining_time":1.705866239},
{"learn":[5.035264888],"iteration":139,"passed_time":0.2760324069,"remaining_time":1.695627642},
{"learn":[5.028771948],"iteration":140,"passed_time":0.276651593,"remaining_time":1.685416443},
{"learn":[5.024912247],"iteration":141,"passed_time":0.2772572104,"remaining_time":1.675258356},
{"learn":[5.02239068],"iteration":142,"passed_time":0.277875886,"remaining_time":1.665312128},
{"learn":[5.017110572],"iteration":143,"passed_time":0.2784971635,"remaining_time":1.655510916},
{"learn":[5.010707886],"iteration":144,"passed_time":0.2791694772,"remaining_time":1.646137262},
{"learn":[5.004389868],"iteration":145,"passed_time":0.2797726776,"remaining_time":1.636478539},
{"learn":[4.997628683],"iteration":146,"passed_time":0.2803931998,"remaining_time":1.627043534},
{"learn":[4.991497851],"iteration":147,"passed_time":0.2810366935,"remaining_time":1.617859884},
{"learn":[4.988345253],"iteration":148,"passed_time":0.2817037638,"remaining_time":1.608925523},
{"learn":[4.98460423],"iteration":149,"passed_time":0.2823644246,"remaining_time":1.600065073},
{"learn":[4.982441783],"iteration":150,"passed_time":0.2830077924,"remaining_time":1.591215998},
{"learn":[4.977461771],"iteration":151,"passed_time":0.2836469403,"remaining_time":1.582451351},
{"learn":[4.973601586],"iteration":152,"passed_time":0.2842966992,"remaining_time":1.573851662},
{"learn":[4.968328804],"iteration":153,"passed_time":0.2849078847,"remaining_time":1.565143314},
{"learn":[4.9640736],"iteration":154,"passed_time":0.2855557259,"remaining_time":1.55673928},
{"learn":[4.960865882],"iteration":155,"passed_time":0.2862013882,"remaining_time":1.548422895},
{"learn":[4.957014156],"iteration":156,"passed_time":0.2868956677,"remaining_time":1.540465273},
{"learn":[4.952244852],"iteration":157,"passed_time":0.2875537199,"remaining_time":1.532406532},
{"learn":[4.949695675],"iteration":158,"passed_time":0.2881732116,"remaining_time":1.524236924},
{"learn":[4.946584698],"iteration":159,"passed_time":0.2888152928,"remaining_time":1.516280287},
{"learn":[4.940192834],"iteration":160,"passed_time":0.2894623796,"remaining_time":1.508440599},
{"learn":[4.936727994],"iteration":161,"passed_time":0.2900873006,"remaining_time":1.500575049},
{"learn":[4.932342063],"iteration":162,"passed_time":0.2906964547,"remaining_time":1.492717378},
{"learn":[4.925830838],"iteration":163,"passed_time":0.2913552951,"remaining_time":1.485201382},
{"learn":[4.922571773],"iteration":164,"passed_time":0.2920097966,"remaining_time":1.477746546},
{"learn":[4.918395814],"iteration":165,"passed_time":0.2926555804,"remaining_time":1.470329844},
{"learn":[4.911142452],"iteration":166,"passed_time":0.2932560714,"remaining_time":1.462768308},
{"learn":[4.908276131],"iteration":167,"passed_time":0.2938844154,"remaining_time":1.455427581},
{"learn":[4.904584645],"iteration":168,"passed_time":0.2944953621,"remaining_time":1.448080745},
{"learn":[4.89795517],"iteration":169,"passed_time":0.2951121114,"remaining_time":1.440841485},
{"learn":[4.895556491],"iteration":170,"passed_time":0.2957538914,"remaining_time":1.433801029},
{"learn":[4.890591233],"iteration":171,"passed_time":0.2964125582,"remaining_time":1.426916269},
{"learn":[4.884629277],"iteration":172,"passed_time":0.2970521236,"remaining_time":1.420012175},
{"learn":[4.880550786],"iteration":173,"passed_time":0.2976997947,"remaining_time":1.413218566},
{"learn":[4.876384842],"iteration":174,"passed_time":0.2983361897,"remaining_time":1.406442037},
{"learn":[4.872638238],"iteration":175,"passed_time":0.2989868142,"remaining_time":1.399801903},
{"learn":[4.869137118],"iteration":176,"passed_time":0.2996238065,"remaining_time":1.393166061},
{"learn":[4.863587157],"iteration":177,"passed_time":0.3003261756,"remaining_time":1.38689953},
{"learn":[4.858028614],"iteration":178,"passed_time":0.3010146157,"remaining_time":1.380631282},
{"learn":[4.853838176],"iteration":179,"passed_time":0.3016825966,"remaining_time":1.374331829},
{"learn":[4.853462329],"iteration":180,"passed_time":0.3020471916,"remaining_time":1.366721823},
{"learn":[4.851573196],"iteration":181,"passed_time":0.3027567879,"remaining_time":1.360742047},
{"learn":[4.848442087],"iteration":182,"passed_time":0.3034394697,"remaining_time":1.354699709},
{"learn":[4.845547104],"iteration":183,"passed_time":0.304107744,"remaining_time":1.348651734},
{"learn":[4.839868817],"iteration":184,"passed_time":0.3047488955,"remaining_time":1.342542431},
{"learn":[4.836336958],"iteration":185,"passed_time":0.3054047157,"remaining_time":1.336556121},
{"learn":[4.831124789],"iteration":186,"passed_time":0.3060242152,"remaining_time":1.330468914},
{"learn":[4.827407333],"iteration":187,"passed_time":0.3066589625,"remaining_time":1.324505732},
{"learn":[4.824088918],"iteration":188,"passed_time":0.3072916506,"remaining_time":1.318590099},
{"learn":[4.820934539],"iteration":189,"passed_time":0.3079017544,"remaining_time":1.312633795},
{"learn":[4.816975227],"iteration":190,"passed_time":0.308521345,"remaining_time":1.306773655},
{"learn":[4.812340486],"iteration":191,"passed_time":0.3091637813,"remaining_time":1.301064246},
{"learn":[4.806402747],"iteration":192,"passed_time":0.3098266915,"remaining_time":1.295492954},
{"learn":[4.801521788],"iteration":193,"passed_time":0.3104581183,"remaining_time":1.28984146},
{"learn":[4.797601172],"iteration":194,"passed_time":0.3110970933,"remaining_time":1.284272616},
{"learn":[4.792694629],"iteration":195,"passed_time":0.3117270546,"remaining_time":1.278717102},
{"learn":[4.789794613],"iteration":196,"passed_time":0.3123271871,"remaining_time":1.273090006},
{"learn":[4.785367055],"iteration":197,"passed_time":0.3129456475,"remaining_time":1.267587926},
{"learn":[4.780376856],"iteration":198,"passed_time":0.3135535436,"remaining_time":1.262092404},
{"learn":[4.776691261],"iteration":199,"passed_time":0.3141880687,"remaining_time":1.256752275},
{"learn":[4.773470753],"iteration":200,"passed_time":0.3148332439,"remaining_time":1.251501303},
{"learn":[4.77207327],"iteration":201,"passed_time":0.3154321176,"remaining_time":1.246113019},
{"learn":[4.767347177],"iteration":202,"passed_time":0.3160521467,"remaining_time":1.24085498},
{"learn":[4.763983068],"iteration":203,"passed_time":0.3166774991,"remaining_time":1.235663183},
{"learn":[4.761588849],"iteration":204,"passed_time":0.3173208947,"remaining_time":1.230585909},
{"learn":[4.758558086],"iteration":205,"passed_time":0.3179785961,"remaining_time":1.225606822},
{"learn":[4.753678804],"iteration":206,"passed_time":0.3186319882,"remaining_time":1.220652979},
{"learn":[4.746510889],"iteration":207,"passed_time":0.3192860756,"remaining_time":1.215743134},
{"learn":[4.744840601],"iteration":208,"passed_time":0.3199219185,"remaining_time":1.210804964},
{"learn":[4.741702222],"iteration":209,"passed_time":0.3205465565,"remaining_time":1.205865617},
{"learn":[4.739352853],"iteration":210,"passed_time":0.3211587984,"remaining_time":1.200920815},
{"learn":[4.735539287],"iteration":211,"passed_time":0.3217710126,"remaining_time":1.196016783},
{"learn":[4.730726751],"iteration":212,"passed_time":0.3224215546,"remaining_time":1.191294664},
{"learn":[4.726416092],"iteration":213,"passed_time":0.3230858955,"remaining_time":1.18666128},
{"learn":[4.721293082],"iteration":214,"passed_time":0.3237095994,"remaining_time":1.181916444},
{"learn":[4.718443695],"iteration":215,"passed_time":0.3243549256,"remaining_time":1.177288249},
{"learn":[4.711627962],"iteration":216,"passed_time":0.3250037079,"remaining_time":1.172709232},
{"learn":[4.709790764],"iteration":217,"passed_time":0.3256114461,"remaining_time":1.168019041},
{"learn":[4.706913073],"iteration":218,"passed_time":0.3262264131,"remaining_time":1.163391912},
{"learn":[4.703846389],"iteration":219,"passed_time":0.326856535,"remaining_time":1.158854988},
{"learn":[4.701001135],"iteration":220,"passed_time":0.3275359804,"remaining_time":1.154527279},
{"learn":[4.700380864],"iteration":221,"passed_time":0.3281527202,"remaining_time":1.150012686},
{"learn":[4.695837486],"iteration":222,"passed_time":0.3287889233,"remaining_time":1.145600867},
{"learn":[4.691242996],"iteration":223,"passed_time":0.3294145874,"remaining_time":1.141186249},
{"learn":[4.690284609],"iteration":224,"passed_time":0.3300635381,"remaining_time":1.13688552},
{"learn":[4.68827119],"iteration":225,"passed_time":0.330681271,"remaining_time":1.132510194},
{"learn":[4.686922425],"iteration":226,"passed_time":0.3312860219,"remaining_time":1.128123766},
{"learn":[4.686085874],"iteration":227,"passed_time":0.3319096077,"remaining_time":1.123834286},
{"learn":[4.683230741],"iteration":228,"passed_time":0.3325138135,"remaining_time":1.119511573},
{"learn":[4.6773487],"iteration":229,"passed_time":0.3331583645,"remaining_time":1.115356264},
{"learn":[4.671462906],"iteration":230,"passed_time":0.3338147204,"remaining_time":1.111270649},
{"learn":[4.664799601],"iteration":231,"passed_time":0.3344630938,"remaining_time":1.107188172},
{"learn":[4.660979386],"iteration":232,"passed_time":0.3350972247,"remaining_time":1.103088289},
{"learn":[4.656281279],"iteration":233,"passed_time":0.3357226995,"remaining_time":1.098989692},
{"learn":[4.651997094],"iteration":234,"passed_time":0.3363435915,"remaining_time":1.094905734},
{"learn":[4.650151977],"iteration":235,"passed_time":0.3369538498,"remaining_time":1.0908167},
{"learn":[4.648478046],"iteration":236,"passed_time":0.3375768253,"remaining_time":1.086797965},
{"learn":[4.646364602],"iteration":237,"passed_time":0.3382138332,"remaining_time":1.082852693},
{"learn":[4.642635873],"iteration":238,"passed_time":0.3388999728,"remaining_time":1.079091545},
{"learn":[4.640860821],"iteration":239,"passed_time":0.3395103682,"remaining_time":1.075116166},
{"learn":[4.639446822],"iteration":240,"passed_time":0.3400906232,"remaining_time":1.071073788},
{"learn":[4.637120072],"iteration":241,"passed_time":0.3406942048,"remaining_time":1.067133088},
{"learn":[4.633769267],"iteration":242,"passed_time":0.3413893815,"remaining_time":1.063505193},
{"learn":[4.630491517],"iteration":243,"passed_time":0.3420226799,"remaining_time":1.059709615},
{"learn":[4.627813333],"iteration":244,"passed_time":0.3426360261,"remaining_time":1.055878366},
{"learn":[4.622496304],"iteration":245,"passed_time":0.3432600825,"remaining_time":1.052106106},
{"learn":[4.618979301],"iteration":246,"passed_time":0.343896454,"remaining_time":1.048396882},
{"learn":[4.616563458],"iteration":247,"passed_time":0.3445624652,"remaining_time":1.044802314},
{"learn":[4.614759385],"iteration":248,"passed_time":0.3451523416,"remaining_time":1.041001641},
{"learn":[4.61251363],"iteration":249,"passed_time":0.3457895752,"remaining_time":1.037368726},
{"learn":[4.608796693],"iteration":250,"passed_time":0.3464524455,"remaining_time":1.033836182},
{"learn":[4.60847774],"iteration":251,"passed_time":0.3470267824,"remaining_time":1.030063624},
{"learn":[4.605195659],"iteration":252,"passed_time":0.347675563,"remaining_time":1.026536148},
{"learn":[4.60103766],"iteration":253,"passed_time":0.3483292615,"remaining_time":1.023045784},
{"learn":[4.599325598],"iteration":254,"passed_time":0.3489540965,"remaining_time":1.019493341},
{"learn":[4.597012808],"iteration":255,"passed_time":0.3495833321,"remaining_time":1.015976559},
{"learn":[4.594161533],"iteration":256,"passed_time":0.3502316595,"remaining_time":1.012537444},
{"learn":[4.592197259],"iteration":257,"passed_time":0.3508604176,"remaining_time":1.009063682},
{"learn":[4.58952828],"iteration":258,"passed_time":0.3514854089,"remaining_time":1.005601112},
{"learn":[4.585816572],"iteration":259,"passed_time":0.352103805,"remaining_time":1.002141599},
{"learn":[4.582934052],"iteration":260,"passed_time":0.352704895,"remaining_time":0.998654856},
{"learn":[4.582234842],"iteration":261,"passed_time":0.3533204949,"remaining_time":0.9952310124},
{"learn":[4.57571562],"iteration":262,"passed_time":0.3539557457,"remaining_time":0.9918835917},
{"learn":[4.571197349],"iteration":263,"passed_time":0.3547204841,"remaining_time":0.9889177134},
{"learn":[4.56723703],"iteration":264,"passed_time":0.3553818252,"remaining_time":0.9856816661},
{"learn":[4.560335567],"iteration":265,"passed_time":0.3560843333,"remaining_time":0.9825785737},
{"learn":[4.554709345],"iteration":266,"passed_time":0.3567218065,"remaining_time":0.9793149219},
{"learn":[4.552806306],"iteration":267,"passed_time":0.357366598,"remaining_time":0.9760908572},
{"learn":[4.550766241],"iteration":268,"passed_time":0.3579802429,"remaining_time":0.9728013291},
{"learn":[4.549216045],"iteration":269,"passed_time":0.3585996339,"remaining_time":0.9695471582},
{"learn":[4.547687452],"iteration":270,"passed_time":0.3592499067,"remaining_time":0.9663955056},
{"learn":[4.545642435],"iteration":271,"passed_time":0.3598501677,"remaining_time":0.9631283901},
{"learn":[4.543930359],"iteration":272,"passed_time":0.3604879079,"remaining_time":0.9599806191},
{"learn":[4.541029943],"iteration":273,"passed_time":0.3611255729,"remaining_time":0.9568509707},
{"learn":[4.537781449],"iteration":274,"passed_time":0.361749927,"remaining_time":0.9537043531},
{"learn":[4.53066128],"iteration":275,"passed_time":0.3623817809,"remaining_time":0.950595686},
{"learn":[4.526763956],"iteration":276,"passed_time":0.3630182106,"remaining_time":0.9475168457},
{"learn":[4.522036004],"iteration":277,"passed_time":0.3636683489,"remaining_time":0.9444911795},
{"learn":[4.515307629],"iteration":278,"passed_time":0.3643086262,"remaining_time":0.941457059},
{"learn":[4.51109143],"iteration":279,"passed_time":0.3649543162,"remaining_time":0.9384539559},
{"learn":[4.508233494],"iteration":280,"passed_time":0.3655803796,"remaining_time":0.9354174126},
{"learn":[4.502555629],"iteration":281,"passed_time":0.366209952,"remaining_time":0.9324068991},
{"learn":[4.500081355],"iteration":282,"passed_time":0.3669225868,"remaining_time":0.9296236562},
{"learn":[4.495281743],"iteration":283,"passed_time":0.3675646116,"remaining_time":0.9266769785},
{"learn":[4.492138869],"iteration":284,"passed_time":0.3685839468,"remaining_time":0.9246930595},
{"learn":[4.491708261],"iteration":285,"passed_time":0.3691932779,"remaining_time":0.9216923093},
{"learn":[4.489398865],"iteration":286,"passed_time":0.369832582,"remaining_time":0.9187826864},
{"learn":[4.485796373],"iteration":287,"passed_time":0.3704753092,"remaining_time":0.9158972921},
{"learn":[4.479542205],"iteration":288,"passed_time":0.3711003942,"remaining_time":0.9129840148},
{"learn":[4.475986993],"iteration":289,"passed_time":0.37172637,"remaining_time":0.9100886989},
{"learn":[4.468661855],"iteration":290,"passed_time":0.3723637989,"remaining_time":0.9072368846},
{"learn":[4.463785664],"iteration":291,"passed_time":0.3730003536,"remaining_time":0.9043981177},
{"learn":[4.460445831],"iteration":292,"passed_time":0.3739859396,"remaining_time":0.9024165845},
{"learn":[4.45692492],"iteration":293,"passed_time":0.3746136837,"remaining_time":0.8995825193},
{"learn":[4.454031688],"iteration":294,"passed_time":0.3752401951,"remaining_time":0.8967604662},
{"learn":[4.451672391],"iteration":295,"passed_time":0.3758682231,"remaining_time":0.8939568548},
{"learn":[4.45031553],"iteration":296,"passed_time":0.376489846,"remaining_time":0.8911527332},
{"learn":[4.446782666],"iteration":297,"passed_time":0.3771266265,"remaining_time":0.8883989657},
{"learn":[4.444369689],"iteration":298,"passed_time":0.3778105948,"remaining_time":0.8857699898},
{"learn":[4.44411683],"iteration":299,"passed_time":0.3784280438,"remaining_time":0.8829987689},
{"learn":[4.440876943],"iteration":300,"passed_time":0.3790699045,"remaining_time":0.8802985491},
{"learn":[4.439336453],"iteration":301,"passed_time":0.3796781583,"remaining_time":0.8775342865},
{"learn":[4.436666901],"iteration":302,"passed_time":0.3802789793,"remaining_time":0.8747671569},
{"learn":[4.433043336],"iteration":303,"passed_time":0.3809204476,"remaining_time":0.8721073405},
{"learn":[4.431419305],"iteration":304,"passed_time":0.3815980491,"remaining_time":0.8695430955},
{"learn":[4.428859646],"iteration":305,"passed_time":0.3822411165,"remaining_time":0.866912859},
{"learn":[4.424552441],"iteration":306,"passed_time":0.3828712732,"remaining_time":0.8642664244},
{"learn":[4.422706391],"iteration":307,"passed_time":0.383487729,"remaining_time":0.8616023003},
{"learn":[4.421427994],"iteration":308,"passed_time":0.3841004033,"remaining_time":0.8589429731},
{"learn":[4.418733158],"iteration":309,"passed_time":0.3847191415,"remaining_time":0.8563103472},
{"learn":[4.415656941],"iteration":310,"passed_time":0.3853729928,"remaining_time":0.8537684631},
{"learn":[4.410747417],"iteration":311,"passed_time":0.3860056462,"remaining_time":0.8511919377},
{"learn":[4.408126521],"iteration":312,"passed_time":0.3866379992,"remaining_time":0.8486271739},
{"learn":[4.407843853],"iteration":313,"passed_time":0.3872093637,"remaining_time":0.8459414761},
{"learn":[4.405219398],"iteration":314,"passed_time":0.3878267962,"remaining_time":0.8433693822},
{"learn":[4.402708465],"iteration":315,"passed_time":0.3884668972,"remaining_time":0.8408587269},
{"learn":[4.40104971],"iteration":316,"passed_time":0.3890926394,"remaining_time":0.8383289361},
{"learn":[4.400830038],"iteration":317,"passed_time":0.3896606321,"remaining_time":0.8356872677},
{"learn":[4.39784288],"iteration":318,"passed_time":0.3902514748,"remaining_time":0.8331073804},
{"learn":[4.393741845],"iteration":319,"passed_time":0.3908790166,"remaining_time":0.8306179104},
{"learn":[4.393425936],"iteration":320,"passed_time":0.3914741748,"remaining_time":0.828071541},
{"learn":[4.390505974],"iteration":321,"passed_time":0.392185016,"remaining_time":0.8257808721},
{"learn":[4.390305136],"iteration":322,"passed_time":0.3927637682,"remaining_time":0.8232231303},
{"learn":[4.38568203],"iteration":323,"passed_time":0.3933879391,"remaining_time":0.8207723668},
{"learn":[4.383057135],"iteration":324,"passed_time":0.3940022473,"remaining_time":0.8183123597},
{"learn":[4.380662684],"iteration":325,"passed_time":0.3946476057,"remaining_time":0.8159278718},
{"learn":[4.37805727],"iteration":326,"passed_time":0.3952722341,"remaining_time":0.8135113564},
{"learn":[4.373708319],"iteration":327,"passed_time":0.3959140731,"remaining_time":0.8111410278},
{"learn":[4.36887921],"iteration":328,"passed_time":0.3965373099,"remaining_time":0.8087432673},
{"learn":[4.367895929],"iteration":329,"passed_time":0.3971790422,"remaining_time":0.8063938129},
{"learn":[4.362140573],"iteration":330,"passed_time":0.3977819483,"remaining_time":0.8039762037},
{"learn":[4.361931924],"iteration":331,"passed_time":0.3983712735,"remaining_time":0.8015422009},
{"learn":[4.359656377],"iteration":332,"passed_time":0.3989879377,"remaining_time":0.7991740374},
{"learn":[4.354281355],"iteration":333,"passed_time":0.3995856976,"remaining_time":0.7967786665},
{"learn":[4.348589447],"iteration":334,"passed_time":0.4002185446,"remaining_time":0.794463678},
{"learn":[4.346355698],"iteration":335,"passed_time":0.4008866227,"remaining_time":0.7922283258},
{"learn":[4.343894047],"iteration":336,"passed_time":0.4015392178,"remaining_time":0.7899718143},
{"learn":[4.341561356],"iteration":337,"passed_time":0.4021835649,"remaining_time":0.7877086389},
{"learn":[4.338869061],"iteration":338,"passed_time":0.4028442969,"remaining_time":0.7854869624},
{"learn":[4.333720063],"iteration":339,"passed_time":0.4034574643,"remaining_time":0.7831821366},
{"learn":[4.330892223],"iteration":340,"passed_time":0.4040978423,"remaining_time":0.7809398184},
{"learn":[4.328311474],"iteration":341,"passed_time":0.4047253538,"remaining_time":0.7786821134},
{"learn":[4.324580133],"iteration":342,"passed_time":0.4053490342,"remaining_time":0.7764265757},
{"learn":[4.323354432],"iteration":343,"passed_time":0.4059333494,"remaining_time":0.774105457},
{"learn":[4.323159553],"iteration":344,"passed_time":0.4065883501,"remaining_time":0.7719286067},
{"learn":[4.318639682],"iteration":345,"passed_time":0.407211468,"remaining_time":0.7697002892},
{"learn":[4.312712208],"iteration":346,"passed_time":0.4078468282,"remaining_time":0.7675042616},
{"learn":[4.311461062],"iteration":347,"passed_time":0.4084361473,"remaining_time":0.7652309426},
{"learn":[4.311178356],"iteration":348,"passed_time":0.4090767527,"remaining_time":0.7630629398},
{"learn":[4.311102505],"iteration":349,"passed_time":0.4096894556,"remaining_time":0.7608518462},
{"learn":[4.310232308],"iteration":350,"passed_time":0.4102825259,"remaining_time":0.7586135593},
{"learn":[4.305128197],"iteration":351,"passed_time":0.4109165943,"remaining_time":0.7564600941},
{"learn":[4.304595496],"iteration":352,"passed_time":0.411509728,"remaining_time":0.7542402096},
{"learn":[4.3004992],"iteration":353,"passed_time":0.412147314,"remaining_time":0.7521106352},
{"learn":[4.297581524],"iteration":354,"passed_time":0.4127946934,"remaining_time":0.7500072599},
{"learn":[4.297355825],"iteration":355,"passed_time":0.4134115139,"remaining_time":0.7478567836},
{"learn":[4.295758715],"iteration":356,"passed_time":0.4140257326,"remaining_time":0.7457102131},
{"learn":[4.292500657],"iteration":357,"passed_time":0.4146601292,"remaining_time":0.7436083881},
{"learn":[4.290797586],"iteration":358,"passed_time":0.4152672649,"remaining_time":0.7414660635},
{"learn":[4.286410608],"iteration":359,"passed_time":0.4159059213,"remaining_time":0.7393883046},
{"learn":[4.280278245],"iteration":360,"passed_time":0.4166112951,"remaining_time":0.7374366137},
{"learn":[4.279941283],"iteration":361,"passed_time":0.4172452255,"remaining_time":0.7353658946},
{"learn":[4.274426275],"iteration":362,"passed_time":0.4178464978,"remaining_time":0.7332457827},
{"learn":[4.273567658],"iteration":363,"passed_time":0.4184734797,"remaining_time":0.7311789371},
{"learn":[4.269488271],"iteration":364,"passed_time":0.4191084953,"remaining_time":0.7291339575},
{"learn":[4.266838205],"iteration":365,"passed_time":0.4197098049,"remaining_time":0.727038296},
{"learn":[4.263456509],"iteration":366,"passed_time":0.4203104878,"remaining_time":0.7249496969},
{"learn":[4.260360204],"iteration":367,"passed_time":0.4209529137,"remaining_time":0.7229408735},
{"learn":[4.255120549],"iteration":368,"passed_time":0.4215804555,"remaining_time":0.7209140039},
{"learn":[4.252582211],"iteration":369,"passed_time":0.4222285477,"remaining_time":0.7189296893},
{"learn":[4.247857931],"iteration":370,"passed_time":0.4228657014,"remaining_time":0.7169340328},
{"learn":[4.245288911],"iteration":371,"passed_time":0.4235638758,"remaining_time":0.7150486935},
{"learn":[4.24048515],"iteration":372,"passed_time":0.4242305979,"remaining_time":0.7131168496},
{"learn":[4.2378365],"iteration":373,"passed_time":0.4248513059,"remaining_time":0.7111147526},
{"learn":[4.236751063],"iteration":374,"passed_time":0.4254757962,"remaining_time":0.7091263271},
{"learn":[4.233240093],"iteration":375,"passed_time":0.4261077134,"remaining_time":0.7071574819},
{"learn":[4.230358421],"iteration":376,"passed_time":0.4267246824,"remaining_time":0.7051710268},
{"learn":[4.225853583],"iteration":377,"passed_time":0.4273491962,"remaining_time":0.7032042329},
{"learn":[4.224702126],"iteration":378,"passed_time":0.4279840251,"remaining_time":0.7012614237},
{"learn":[4.224361982],"iteration":379,"passed_time":0.4285823232,"remaining_time":0.6992658958},
{"learn":[4.223787954],"iteration":380,"passed_time":0.4291763337,"remaining_time":0.6972707364},
{"learn":[4.22144054],"iteration":381,"passed_time":0.4297660052,"remaining_time":0.6952758933},
{"learn":[4.217739335],"iteration":382,"passed_time":0.4304140149,"remaining_time":0.6933823687},
{"learn":[4.215611665],"iteration":383,"passed_time":0.4310364565,"remaining_time":0.6914543157},
{"learn":[4.210236863],"iteration":384,"passed_time":0.4316566167,"remaining_time":0.6895294007},
{"learn":[4.208454294],"iteration":385,"passed_time":0.4322829223,"remaining_time":0.6876210215},
{"learn":[4.207446501],"iteration":386,"passed_time":0.4328957451,"remaining_time":0.6856979114},
{"learn":[4.204985442],"iteration":387,"passed_time":0.4335595902,"remaining_time":0.6838620341},
{"learn":[4.202796622],"iteration":388,"passed_time":0.4341917783,"remaining_time":0.681982459},
{"learn":[4.199774004],"iteration":389,"passed_time":0.434820506,"remaining_time":0.6801038684},
{"learn":[4.199458358],"iteration":390,"passed_time":0.4354030728,"remaining_time":0.6781597733},
{"learn":[4.19751254],"iteration":391,"passed_time":0.4360351541,"remaining_time":0.6762994227},
{"learn":[4.195201346],"iteration":392,"passed_time":0.4366788848,"remaining_time":0.6744633157},
{"learn":[4.190593508],"iteration":393,"passed_time":0.4373151843,"remaining_time":0.6726218316},
{"learn":[4.187212054],"iteration":394,"passed_time":0.437924755,"remaining_time":0.6707455109},
{"learn":[4.184984466],"iteration":395,"passed_time":0.4385463407,"remaining_time":0.6688939135},
{"learn":[4.182832144],"iteration":396,"passed_time":0.4392097934,"remaining_time":0.6671121044},
{"learn":[4.179752812],"iteration":397,"passed_time":0.4398482624,"remaining_time":0.6652981255},
{"learn":[4.17878934],"iteration":398,"passed_time":0.4404918255,"remaining_time":0.6634977121},
{"learn":[4.174548229],"iteration":399,"passed_time":0.4411170295,"remaining_time":0.6616755442},
{"learn":[4.168872556],"iteration":400,"passed_time":0.441736773,"remaining_time":0.6598511895},
{"learn":[4.163926494],"iteration":401,"passed_time":0.4423901928,"remaining_time":0.6580829236},
{"learn":[4.159485076],"iteration":402,"passed_time":0.4430321351,"remaining_time":0.6563031878},
{"learn":[4.155926102],"iteration":403,"passed_time":0.443656135,"remaining_time":0.654502615},
{"learn":[4.153540115],"iteration":404,"passed_time":0.4443021532,"remaining_time":0.6527402004},
{"learn":[4.150983044],"iteration":405,"passed_time":0.4449417715,"remaining_time":0.6509739219},
{"learn":[4.146539132],"iteration":406,"passed_time":0.4455708838,"remaining_time":0.6491978725},
{"learn":[4.144869174],"iteration":407,"passed_time":0.4461750418,"remaining_time":0.6473912372},
{"learn":[4.142825962],"iteration":408,"passed_time":0.4468261516,"remaining_time":0.6456583266},
{"learn":[4.142467378],"iteration":409,"passed_time":0.4474440346,"remaining_time":0.6438828791},
{"learn":[4.141800768],"iteration":410,"passed_time":0.4480758407,"remaining_time":0.6421330175},
{"learn":[4.140107084],"iteration":411,"passed_time":0.4486851493,"remaining_time":0.6403564752},
{"learn":[4.136243196],"iteration":412,"passed_time":0.4493511578,"remaining_time":0.6386661735},
{"learn":[4.133618439],"iteration":413,"passed_time":0.4499882812,"remaining_time":0.6369399343},
{"learn":[4.131053025],"iteration":414,"passed_time":0.4506228392,"remaining_time":0.6352153276},
{"learn":[4.128379975],"iteration":415,"passed_time":0.4512326835,"remaining_time":0.6334612672},
{"learn":[4.127068571],"iteration":416,"passed_time":0.4518708408,"remaining_time":0.6317522786},
{"learn":[4.125969877],"iteration":417,"passed_time":0.4524743728,"remaining_time":0.6300002033},
{"learn":[4.123893633],"iteration":418,"passed_time":0.4530914763,"remaining_time":0.628272429},
{"learn":[4.119643722],"iteration":419,"passed_time":0.4537248112,"remaining_time":0.6265723583},
{"learn":[4.11465686],"iteration":420,"passed_time":0.4543794247,"remaining_time":0.6249066197},
{"learn":[4.111565986],"iteration":421,"passed_time":0.4549776386,"remaining_time":0.6231684244},
{"learn":[4.106322452],"iteration":422,"passed_time":0.4555999222,"remaining_time":0.6214684518},
{"learn":[4.104222175],"iteration":423,"passed_time":0.4562324975,"remaining_time":0.6197875437},
{"learn":[4.103008002],"iteration":424,"passed_time":0.4568263404,"remaining_time":0.6180591664},
{"learn":[4.099176337],"iteration":425,"passed_time":0.4574387377,"remaining_time":0.6163611161},
{"learn":[4.096525716],"iteration":426,"passed_time":0.4580800524,"remaining_time":0.6147069556},
{"learn":[4.094967724],"iteration":427,"passed_time":0.4587195041,"remaining_time":0.6130550382},
{"learn":[4.094683584],"iteration":428,"passed_time":0.4592981635,"remaining_time":0.6113269262},
{"learn":[4.091096563],"iteration":429,"passed_time":0.4599154128,"remaining_time":0.6096553146},
{"learn":[4.089178677],"iteration":430,"passed_time":0.4605348298,"remaining_time":0.6079914575},
{"learn":[4.085335077],"iteration":431,"passed_time":0.4611872774,"remaining_time":0.6063758647},
{"learn":[4.084852122],"iteration":432,"passed_time":0.4618255875,"remaining_time":0.6047462081},
{"learn":[4.080322952],"iteration":433,"passed_time":0.4624355133,"remaining_time":0.6030841026},
{"learn":[4.077449519],"iteration":434,"passed_time":0.463052938,"remaining_time":0.6014365746},
{"learn":[4.076568374],"iteration":435,"passed_time":0.4636858761,"remaining_time":0.5998138397},
{"learn":[4.076071793],"iteration":436,"passed_time":0.4643062585,"remaining_time":0.5981794589},
{"learn":[4.075027644],"iteration":437,"passed_time":0.4649270967,"remaining_time":0.596550293},
{"learn":[4.07020837],"iteration":438,"passed_time":0.4655532287,"remaining_time":0.5949324859},
{"learn":[4.06833694],"iteration":439,"passed_time":0.4661748543,"remaining_time":0.5933134509},
{"learn":[4.063936568],"iteration":440,"passed_time":0.4668187481,"remaining_time":0.591727166},
{"learn":[4.061734926],"iteration":441,"passed_time":0.4674379099,"remaining_time":0.5901139225},
{"learn":[4.060815619],"iteration":442,"passed_time":0.4680706458,"remaining_time":0.5885222341},
{"learn":[4.056407489],"iteration":443,"passed_time":0.468715222,"remaining_time":0.5869496924},
{"learn":[4.05238936],"iteration":444,"passed_time":0.4693300562,"remaining_time":0.5853442274},
{"learn":[4.049685254],"iteration":445,"passed_time":0.4699497676,"remaining_time":0.5837492629},
{"learn":[4.045162016],"iteration":446,"passed_time":0.4705683078,"remaining_time":0.582157213},
{"learn":[4.042955482],"iteration":447,"passed_time":0.4712099619,"remaining_time":0.5805979888},
{"learn":[4.041467663],"iteration":448,"passed_time":0.4718218167,"remaining_time":0.5790062829},
{"learn":[4.038920476],"iteration":449,"passed_time":0.472437697,"remaining_time":0.5774238519},
{"learn":[4.036694383],"iteration":450,"passed_time":0.4730795881,"remaining_time":0.57587737},
{"learn":[4.034999007],"iteration":451,"passed_time":0.4736922399,"remaining_time":0.5742994413},
{"learn":[4.031928018],"iteration":452,"passed_time":0.4743082921,"remaining_time":0.5727298803},
{"learn":[4.028718143],"iteration":453,"passed_time":0.4749236454,"remaining_time":0.5711636793},
{"learn":[4.027401978],"iteration":454,"passed_time":0.4755510874,"remaining_time":0.5696161377},
{"learn":[4.025930598],"iteration":455,"passed_time":0.4761515923,"remaining_time":0.5680404961},
{"learn":[4.021074523],"iteration":456,"passed_time":0.476791617,"remaining_time":0.5665160788},
{"learn":[4.020268486],"iteration":457,"passed_time":0.4774051455,"remaining_time":0.5649641678},
{"learn":[4.017986361],"iteration":458,"passed_time":0.4780321517,"remaining_time":0.5634322311},
{"learn":[4.014814804],"iteration":459,"passed_time":0.4786570423,"remaining_time":0.5619017453},
{"learn":[4.009704796],"iteration":460,"passed_time":0.4792704389,"remaining_time":0.5603617496},
{"learn":[4.008440457],"iteration":461,"passed_time":0.4798715428,"remaining_time":0.5588114503},
{"learn":[4.004854849],"iteration":462,"passed_time":0.480488925,"remaining_time":0.5572841311},
{"learn":[4.000898028],"iteration":463,"passed_time":0.481113859,"remaining_time":0.5557694578},
{"learn":[3.996617985],"iteration":464,"passed_time":0.4817265619,"remaining_time":0.554244539},
{"learn":[3.995443319],"iteration":465,"passed_time":0.4823331081,"remaining_time":0.5527164801},
{"learn":[3.990771995],"iteration":466,"passed_time":0.4829664057,"remaining_time":0.5512228998},
{"learn":[3.989249359],"iteration":467,"passed_time":0.4835679324,"remaining_time":0.5496968804},
{"learn":[3.986599538],"iteration":468,"passed_time":0.4841907924,"remaining_time":0.5481989569},
{"learn":[3.985628919],"iteration":469,"passed_time":0.4848294793,"remaining_time":0.5467226043},
{"learn":[3.985086112],"iteration":470,"passed_time":0.4854293548,"remaining_time":0.545206218},
{"learn":[3.98466839],"iteration":471,"passed_time":0.4860231543,"remaining_time":0.5436869183},
{"learn":[3.984233894],"iteration":472,"passed_time":0.4866335853,"remaining_time":0.5421900623},
{"learn":[3.981855845],"iteration":473,"passed_time":0.4872433427,"remaining_time":0.5406961989},
{"learn":[3.978684264],"iteration":474,"passed_time":0.4878898662,"remaining_time":0.5392466942},
{"learn":[3.974361269],"iteration":475,"passed_time":0.4885122809,"remaining_time":0.5377740235},
{"learn":[3.972074049],"iteration":476,"passed_time":0.4891327961,"remaining_time":0.5363028351},
{"learn":[3.97191982],"iteration":477,"passed_time":0.4897662716,"remaining_time":0.5348493594},
{"learn":[3.969616848],"iteration":478,"passed_time":0.4903818984,"remaining_time":0.5333798937},
{"learn":[3.968533527],"iteration":479,"passed_time":0.4910143799,"remaining_time":0.5319322449},
{"learn":[3.967568753],"iteration":480,"passed_time":0.4916263067,"remaining_time":0.5304658071},
{"learn":[3.966232553],"iteration":481,"passed_time":0.4922374748,"remaining_time":0.5290020995},
{"learn":[3.961522393],"iteration":482,"passed_time":0.4928364814,"remaining_time":0.5275289045},
{"learn":[3.955829553],"iteration":483,"passed_time":0.4934585132,"remaining_time":0.5260838695},
{"learn":[3.954248095],"iteration":484,"passed_time":0.4941128376,"remaining_time":0.5246765183},
{"learn":[3.951922606],"iteration":485,"passed_time":0.4947859292,"remaining_time":0.5232921144},
{"learn":[3.94978202],"iteration":486,"passed_time":0.4953877988,"remaining_time":0.5218356074},
{"learn":[3.949518999],"iteration":487,"passed_time":0.495942912,"remaining_time":0.520333547},
{"learn":[3.945431216],"iteration":488,"passed_time":0.496554436,"remaining_time":0.5188943084},
{"learn":[3.943249086],"iteration":489,"passed_time":0.4971847932,"remaining_time":0.5174780501},
{"learn":[3.941981548],"iteration":490,"passed_time":0.4978067356,"remaining_time":0.5160562697},
{"learn":[3.936600517],"iteration":491,"passed_time":0.4983922237,"remaining_time":0.5146001009},
{"learn":[3.934476885],"iteration":492,"passed_time":0.4989722886,"remaining_time":0.513141887},
{"learn":[3.93045798],"iteration":493,"passed_time":0.4996335537,"remaining_time":0.5117704011},
{"learn":[3.925977375],"iteration":494,"passed_time":0.5002938083,"remaining_time":0.5104007539},
{"learn":[3.92457993],"iteration":495,"passed_time":0.500977405,"remaining_time":0.5090576858},
{"learn":[3.919849146],"iteration":496,"passed_time":0.501628487,"remaining_time":0.5076843641},
{"learn":[3.919681964],"iteration":497,"passed_time":0.5022637274,"remaining_time":0.5062979742},
{"learn":[3.917633027],"iteration":498,"passed_time":0.5029368216,"remaining_time":0.5049526004},
{"learn":[3.916616419],"iteration":499,"passed_time":0.5035679167,"remaining_time":0.5035679167},
{"learn":[3.912896166],"iteration":500,"passed_time":0.5042507452,"remaining_time":0.5022377681},
{"learn":[3.912769674],"iteration":501,"passed_time":0.5048713654,"remaining_time":0.500848486},
{"learn":[3.909373788],"iteration":502,"passed_time":0.5055098353,"remaining_time":0.4994798969},
{"learn":[3.906706036],"iteration":503,"passed_time":0.5061860669,"remaining_time":0.4981513674},
{"learn":[3.903895664],"iteration":504,"passed_time":0.5067981665,"remaining_time":0.4967625592},
{"learn":[3.902982967],"iteration":505,"passed_time":0.5074158629,"remaining_time":0.4953822851},
{"learn":[3.900905528],"iteration":506,"passed_time":0.5080152549,"remaining_time":0.4939872202},
{"learn":[3.897463465],"iteration":507,"passed_time":0.5086521846,"remaining_time":0.4926316434},
{"learn":[3.895918033],"iteration":508,"passed_time":0.5092556351,"remaining_time":0.491246595},
{"learn":[3.893921936],"iteration":509,"passed_time":0.5098651477,"remaining_time":0.489870436},
{"learn":[3.890237934],"iteration":510,"passed_time":0.5104936896,"remaining_time":0.4885154877},
{"learn":[3.887311613],"iteration":511,"passed_time":0.5111126622,"remaining_time":0.4871542561},
{"learn":[3.884869735],"iteration":512,"passed_time":0.5117805624,"remaining_time":0.4858423662},
{"learn":[3.882101231],"iteration":513,"passed_time":0.5123994308,"remaining_time":0.4844866213},
{"learn":[3.88060368],"iteration":514,"passed_time":0.5130309972,"remaining_time":0.4831456964},
{"learn":[3.877726076],"iteration":515,"passed_time":0.5136492979,"remaining_time":0.4817950779},
{"learn":[3.874938145],"iteration":516,"passed_time":0.5142657303,"remaining_time":0.4804455469},
{"learn":[3.874340833],"iteration":517,"passed_time":0.5148858801,"remaining_time":0.4791023054},
{"learn":[3.873105224],"iteration":518,"passed_time":0.5154950254,"remaining_time":0.4777516517},
{"learn":[3.869800236],"iteration":519,"passed_time":0.5161406616,"remaining_time":0.4764375338},
{"learn":[3.867932518],"iteration":520,"passed_time":0.5167498252,"remaining_time":0.4750924497},
{"learn":[3.866666962],"iteration":521,"passed_time":0.5173735604,"remaining_time":0.4737635284},
{"learn":[3.865527652],"iteration":522,"passed_time":0.5180158239,"remaining_time":0.4724542027},
{"learn":[3.861900081],"iteration":523,"passed_time":0.5186684789,"remaining_time":0.4711568625},
{"learn":[3.858502887],"iteration":524,"passed_time":0.5192619563,"remaining_time":0.4698084367},
{"learn":[3.858335097],"iteration":525,"passed_time":0.5198476823,"remaining_time":0.4684558962},
{"learn":[3.855719306],"iteration":526,"passed_time":0.5204697705,"remaining_time":0.4671389022},
{"learn":[3.855137428],"iteration":527,"passed_time":0.5211199818,"remaining_time":0.4658496807},
{"learn":[3.851985706],"iteration":528,"passed_time":0.5217843782,"remaining_time":0.464575505},
{"learn":[3.851051809],"iteration":529,"passed_time":0.5223973017,"remaining_time":0.4632579845},
{"learn":[3.850679146],"iteration":530,"passed_time":0.5230091955,"remaining_time":0.4619422085},
{"learn":[3.848179484],"iteration":531,"passed_time":0.5236383365,"remaining_time":0.4606442509},
{"learn":[3.844551071],"iteration":532,"passed_time":0.5242838563,"remaining_time":0.4593631537},
{"learn":[3.841604794],"iteration":533,"passed_time":0.5249240086,"remaining_time":0.4580797528},
{"learn":[3.83969656],"iteration":534,"passed_time":0.5255372897,"remaining_time":0.4567754013},
{"learn":[3.836811463],"iteration":535,"passed_time":0.5261384396,"remaining_time":0.4554631269},
{"learn":[3.834182551],"iteration":536,"passed_time":0.5267604038,"remaining_time":0.4541714468},
{"learn":[3.828012842],"iteration":537,"passed_time":0.5273978266,"remaining_time":0.4528955314},
{"learn":[3.826636176],"iteration":538,"passed_time":0.5280487706,"remaining_time":0.4516335496},
{"learn":[3.826189798],"iteration":539,"passed_time":0.52864105,"remaining_time":0.4503238574},
{"learn":[3.824104738],"iteration":540,"passed_time":0.5292526782,"remaining_time":0.4490332334},
{"learn":[3.82300218],"iteration":541,"passed_time":0.5298528758,"remaining_time":0.4477354559},
{"learn":[3.817146402],"iteration":542,"passed_time":0.5304749259,"remaining_time":0.4464586393},
{"learn":[3.814638044],"iteration":543,"passed_time":0.531107857,"remaining_time":0.4451933508},
{"learn":[3.812979573],"iteration":544,"passed_time":0.5317394365,"remaining_time":0.4439292544},
{"learn":[3.811938825],"iteration":545,"passed_time":0.5323479187,"remaining_time":0.4426482694},
{"learn":[3.811479418],"iteration":546,"passed_time":0.5329404577,"remaining_time":0.4413565399},
{"learn":[3.80742981],"iteration":547,"passed_time":0.5335585074,"remaining_time":0.4400884039},
{"learn":[3.805097043],"iteration":548,"passed_time":0.5342005513,"remaining_time":0.4388423472},
{"learn":[3.801577232],"iteration":549,"passed_time":0.5348099111,"remaining_time":0.4375717455},
{"learn":[3.799762083],"iteration":550,"passed_time":0.5354366517,"remaining_time":0.4363177071},
{"learn":[3.796393455],"iteration":551,"passed_time":0.5360181924,"remaining_time":0.4350292576},
{"learn":[3.793486459],"iteration":552,"passed_time":0.5366600895,"remaining_time":0.4337921519},
{"learn":[3.792006091],"iteration":553,"passed_time":0.5373065687,"remaining_time":0.4325608838},
{"learn":[3.78932128],"iteration":554,"passed_time":0.5379471672,"remaining_time":0.4313270079},
{"learn":[3.787581812],"iteration":555,"passed_time":0.5385919509,"remaining_time":0.4300986083},
{"learn":[3.785308865],"iteration":556,"passed_time":0.5392203591,"remaining_time":0.4288592802},
{"learn":[3.78465475],"iteration":557,"passed_time":0.5398382613,"remaining_time":0.4276138199},
{"learn":[3.780498869],"iteration":558,"passed_time":0.5404698304,"remaining_time":0.4263813868},
{"learn":[3.778734909],"iteration":559,"passed_time":0.541073003,"remaining_time":0.4251287881},
{"learn":[3.778652349],"iteration":560,"passed_time":0.5416557478,"remaining_time":0.4238625192},
{"learn":[3.777928006],"iteration":561,"passed_time":0.5422719163,"remaining_time":0.4226247319},
{"learn":[3.776131406],"iteration":562,"passed_time":0.5428653347,"remaining_time":0.4213714943},
{"learn":[3.772925617],"iteration":563,"passed_time":0.5434822698,"remaining_time":0.4201387759},
{"learn":[3.7727745],"iteration":564,"passed_time":0.5440732114,"remaining_time":0.4188882247},
{"learn":[3.771763073],"iteration":565,"passed_time":0.5446897228,"remaining_time":0.4176596108},
{"learn":[3.768738162],"iteration":566,"passed_time":0.5453283021,"remaining_time":0.4164500084},
{"learn":[3.767220794],"iteration":567,"passed_time":0.5459499189,"remaining_time":0.4152295158},
{"learn":[3.766691102],"iteration":568,"passed_time":0.5466043319,"remaining_time":0.4140359702},
{"learn":[3.766259335],"iteration":569,"passed_time":0.5472040512,"remaining_time":0.4128030561},
{"learn":[3.76116362],"iteration":570,"passed_time":0.5478402456,"remaining_time":0.4115997642},
{"learn":[3.758633056],"iteration":571,"passed_time":0.5484697651,"remaining_time":0.4103934606},
{"learn":[3.754603809],"iteration":572,"passed_time":0.5491048483,"remaining_time":0.4091933163},
{"learn":[3.754070549],"iteration":573,"passed_time":0.549716763,"remaining_time":0.4079779461},
{"learn":[3.750534319],"iteration":574,"passed_time":0.550338873,"remaining_time":0.4067722105},
{"learn":[3.746491516],"iteration":575,"passed_time":0.5509515534,"remaining_time":0.4055615601},
{"learn":[3.744210544],"iteration":576,"passed_time":0.5515448216,"remaining_time":0.4043387514},
{"learn":[3.742929991],"iteration":577,"passed_time":0.5521945701,"remaining_time":0.4031593574},
{"learn":[3.740402992],"iteration":578,"passed_time":0.5528271792,"remaining_time":0.4019693307},
{"learn":[3.739644243],"iteration":579,"passed_time":0.5534504152,"remaining_time":0.4007744386},
{"learn":[3.737529404],"iteration":580,"passed_time":0.5540812194,"remaining_time":0.3995869724},
{"learn":[3.737196923],"iteration":581,"passed_time":0.5547142018,"remaining_time":0.3984029834},
{"learn":[3.733954464],"iteration":582,"passed_time":0.5553511498,"remaining_time":0.3972237212},
{"learn":[3.731608623],"iteration":583,"passed_time":0.5559725922,"remaining_time":0.3960352712},
{"learn":[3.729843952],"iteration":584,"passed_time":0.5565789014,"remaining_time":0.3948380241},
{"learn":[3.727223798],"iteration":585,"passed_time":0.5572009506,"remaining_time":0.3936539139},
{"learn":[3.725351667],"iteration":586,"passed_time":0.5578522435,"remaining_time":0.392492294},
{"learn":[3.725026912],"iteration":587,"passed_time":0.5584852077,"remaining_time":0.3913195673},
{"learn":[3.721974565],"iteration":588,"passed_time":0.5592222125,"remaining_time":0.3902212722},
{"learn":[3.720269493],"iteration":589,"passed_time":0.5598676169,"remaining_time":0.3890605474},
{"learn":[3.718907466],"iteration":590,"passed_time":0.5604937689,"remaining_time":0.3878882428},
{"learn":[3.715602912],"iteration":591,"passed_time":0.5611238952,"remaining_time":0.3867205223},
{"learn":[3.714463059],"iteration":592,"passed_time":0.5617286122,"remaining_time":0.3855371757},
{"learn":[3.710802077],"iteration":593,"passed_time":0.5623730261,"remaining_time":0.3843829101},
{"learn":[3.708032435],"iteration":594,"passed_time":0.5629889307,"remaining_time":0.3832109528},
{"learn":[3.703788939],"iteration":595,"passed_time":0.5635848736,"remaining_time":0.3820273304},
{"learn":[3.702500944],"iteration":596,"passed_time":0.5641869368,"remaining_time":0.3808498083},
{"learn":[3.698196925],"iteration":597,"passed_time":0.5648498991,"remaining_time":0.3797151496},
{"learn":[3.69658891],"iteration":598,"passed_time":0.5654856769,"remaining_time":0.3785638672},
{"learn":[3.696124066],"iteration":599,"passed_time":0.5661329721,"remaining_time":0.3774219814},
{"learn":[3.693537052],"iteration":600,"passed_time":0.5667741609,"remaining_time":0.3762776875},
{"learn":[3.691343275],"iteration":601,"passed_time":0.5674227166,"remaining_time":0.3751399356},
{"learn":[3.690973831],"iteration":602,"passed_time":0.5680523315,"remaining_time":0.373991336},
{"learn":[3.686151073],"iteration":603,"passed_time":0.5687197291,"remaining_time":0.3728692263},
{"learn":[3.683921982],"iteration":604,"passed_time":0.5693439512,"remaining_time":0.3717204309},
{"learn":[3.679975271],"iteration":605,"passed_time":0.5699558173,"remaining_time":0.3705653333},
{"learn":[3.674047638],"iteration":606,"passed_time":0.5705941491,"remaining_time":0.3694291608},
{"learn":[3.673151794],"iteration":607,"passed_time":0.571215588,"remaining_time":0.3682837344},
{"learn":[3.670953108],"iteration":608,"passed_time":0.5718345388,"remaining_time":0.3671384313},
{"learn":[3.6703947],"iteration":609,"passed_time":0.5724506848,"remaining_time":0.3659930608},
{"learn":[3.668433805],"iteration":610,"passed_time":0.5731247027,"remaining_time":0.3648862673},
{"learn":[3.668304956],"iteration":611,"passed_time":0.5737554175,"remaining_time":0.3637534346},
{"learn":[3.667880012],"iteration":612,"passed_time":0.5743894651,"remaining_time":0.3626243442},
{"learn":[3.667282264],"iteration":613,"passed_time":0.5750309117,"remaining_time":0.3615015178},
{"learn":[3.664611483],"iteration":614,"passed_time":0.575676646,"remaining_time":0.360382941},
{"learn":[3.662543394],"iteration":615,"passed_time":0.5763266975,"remaining_time":0.3592685907},
{"learn":[3.659041959],"iteration":616,"passed_time":0.5769249835,"remaining_time":0.3581236121},
{"learn":[3.656868545],"iteration":617,"passed_time":0.5776115345,"remaining_time":0.3570349615},
{"learn":[3.654785614],"iteration":618,"passed_time":0.5782923854,"remaining_time":0.3559441015},
{"learn":[3.654566096],"iteration":619,"passed_time":0.5789233468,"remaining_time":0.3548239868},
{"learn":[3.651007045],"iteration":620,"passed_time":0.5795515502,"remaining_time":0.3537037641},
{"learn":[3.648921786],"iteration":621,"passed_time":0.5802282732,"remaining_time":0.3526146097},
{"learn":[3.647655706],"iteration":622,"passed_time":0.5808463811,"remaining_time":0.3514913092},
{"learn":[3.647241144],"iteration":623,"passed_time":0.5814845523,"remaining_time":0.3503817174},
{"learn":[3.644195689],"iteration":624,"passed_time":0.582087211,"remaining_time":0.3492523266},
{"learn":[3.642632246],"iteration":625,"passed_time":0.5826964623,"remaining_time":0.3481285573},
{"learn":[3.642523322],"iteration":626,"passed_time":0.5831759043,"remaining_time":0.3469292062},
{"learn":[3.641494659],"iteration":627,"passed_time":0.5837946937,"remaining_time":0.3458146912},
{"learn":[3.63976496],"iteration":628,"passed_time":0.5844243955,"remaining_time":0.3447081887},
{"learn":[3.637945652],"iteration":629,"passed_time":0.5850688892,"remaining_time":0.3436118873},
{"learn":[3.636233667],"iteration":630,"passed_time":0.5857178746,"remaining_time":0.3425196446},
{"learn":[3.635304404],"iteration":631,"passed_time":0.5863120118,"remaining_time":0.3413968677},
{"learn":[3.632234951],"iteration":632,"passed_time":0.5869514835,"remaining_time":0.3403020449},
{"learn":[3.631630987],"iteration":633,"passed_time":0.5875759721,"remaining_time":0.3392000092},
{"learn":[3.630301009],"iteration":634,"passed_time":0.5882098938,"remaining_time":0.3381048996},
{"learn":[3.629077964],"iteration":635,"passed_time":0.5888344858,"remaining_time":0.3370059007},
{"learn":[3.628004522],"iteration":636,"passed_time":0.5894755123,"remaining_time":0.3359177566},
{"learn":[3.625062876],"iteration":637,"passed_time":0.5900978297,"remaining_time":0.3348203987},
{"learn":[3.624917986],"iteration":638,"passed_time":0.5907030972,"remaining_time":0.3337148953},
{"learn":[3.622887087],"iteration":639,"passed_time":0.5913285043,"remaining_time":0.3326222837},
{"learn":[3.621220865],"iteration":640,"passed_time":0.5919526084,"remaining_time":0.3315304},
{"learn":[3.621143844],"iteration":641,"passed_time":0.5925325048,"remaining_time":0.330415322},
{"learn":[3.620822821],"iteration":642,"passed_time":0.5931518489,"remaining_time":0.3293238104},
{"learn":[3.619202826],"iteration":643,"passed_time":0.5937560338,"remaining_time":0.3282253852},
{"learn":[3.618204882],"iteration":644,"passed_time":0.5944064265,"remaining_time":0.3271539247},
{"learn":[3.614259666],"iteration":645,"passed_time":0.5950365814,"remaining_time":0.3260726777},
{"learn":[3.613415661],"iteration":646,"passed_time":0.5956577278,"remaining_time":0.3249879102},
{"learn":[3.611096773],"iteration":647,"passed_time":0.5962889079,"remaining_time":0.3239100241},
{"learn":[3.610820695],"iteration":648,"passed_time":0.5969038073,"remaining_time":0.3228247093},
{"learn":[3.609290065],"iteration":649,"passed_time":0.597520659,"remaining_time":0.3217418933},
{"learn":[3.60897947],"iteration":650,"passed_time":0.598149279,"remaining_time":0.3206668178},
{"learn":[3.606570702],"iteration":651,"passed_time":0.5987703499,"remaining_time":0.3195890824},
{"learn":[3.606292637],"iteration":652,"passed_time":0.5994571058,"remaining_time":0.3185476504},
{"learn":[3.602753838],"iteration":653,"passed_time":0.6001122523,"remaining_time":0.31749058},
{"learn":[3.599755869],"iteration":654,"passed_time":0.600752316,"remaining_time":0.3164267924},
{"learn":[3.599509575],"iteration":655,"passed_time":0.60135444,"remaining_time":0.3153444015},
{"learn":[3.595337722],"iteration":656,"passed_time":0.6019867643,"remaining_time":0.3142792392},
{"learn":[3.595168561],"iteration":657,"passed_time":0.6026019059,"remaining_time":0.3132064617},
{"learn":[3.59290559],"iteration":658,"passed_time":0.6032318324,"remaining_time":0.3121427236},
{"learn":[3.592015928],"iteration":659,"passed_time":0.6038525369,"remaining_time":0.3110755493},
{"learn":[3.590680403],"iteration":660,"passed_time":0.6044788313,"remaining_time":0.3100125927},
{"learn":[3.590361532],"iteration":661,"passed_time":0.6051053574,"remaining_time":0.3089510737},
{"learn":[3.589069739],"iteration":662,"passed_time":0.6057354168,"remaining_time":0.3078926629},
{"learn":[3.585010186],"iteration":663,"passed_time":0.6063464617,"remaining_time":0.3068259204},
{"learn":[3.582997552],"iteration":664,"passed_time":0.606973757,"remaining_time":0.3057687347},
{"learn":[3.582119256],"iteration":665,"passed_time":0.6075975832,"remaining_time":0.3047111003},
{"learn":[3.579019356],"iteration":666,"passed_time":0.6082421369,"remaining_time":0.3036651148},
{"learn":[3.57719559],"iteration":667,"passed_time":0.6088696978,"remaining_time":0.3026118857},
{"learn":[3.574050046],"iteration":668,"passed_time":0.6095051761,"remaining_time":0.3015638465},
{"learn":[3.572204518],"iteration":669,"passed_time":0.6101295536,"remaining_time":0.3005115712},
{"learn":[3.569508025],"iteration":670,"passed_time":0.6107736272,"remaining_time":0.2994702285},
{"learn":[3.566268704],"iteration":671,"passed_time":0.6113822942,"remaining_time":0.2984127865},
{"learn":[3.562564052],"iteration":672,"passed_time":0.6120151065,"remaining_time":0.2973684098},
{"learn":[3.561173586],"iteration":673,"passed_time":0.6126509815,"remaining_time":0.2963267358},
{"learn":[3.559551904],"iteration":674,"passed_time":0.6133102282,"remaining_time":0.2952975173},
{"learn":[3.558593054],"iteration":675,"passed_time":0.6139252308,"remaining_time":0.2942481875},
{"learn":[3.555647008],"iteration":676,"passed_time":0.6145575465,"remaining_time":0.293208401},
{"learn":[3.553100059],"iteration":677,"passed_time":0.6151674428,"remaining_time":0.292159169},
{"learn":[3.55085578],"iteration":678,"passed_time":0.6158196099,"remaining_time":0.2911312147},
{"learn":[3.550737965],"iteration":679,"passed_time":0.6164170903,"remaining_time":0.2900786307},
{"learn":[3.549408772],"iteration":680,"passed_time":0.617047338,"remaining_time":0.2890427325},
{"learn":[3.547390589],"iteration":681,"passed_time":0.6176713631,"remaining_time":0.2880051224},
{"learn":[3.54723575],"iteration":682,"passed_time":0.6182932022,"remaining_time":0.2869677088},
{"learn":[3.543988891],"iteration":683,"passed_time":0.6189363608,"remaining_time":0.2859413597},
{"learn":[3.543868508],"iteration":684,"passed_time":0.6195536839,"remaining_time":0.2849042488},
{"learn":[3.542752124],"iteration":685,"passed_time":0.6201721426,"remaining_time":0.2838688816},
{"learn":[3.541334315],"iteration":686,"passed_time":0.6208033036,"remaining_time":0.2828405153},
{"learn":[3.540208266],"iteration":687,"passed_time":0.6214288722,"remaining_time":0.2818107676},
{"learn":[3.537730983],"iteration":688,"passed_time":0.6220798353,"remaining_time":0.2807936557},
{"learn":[3.53419867],"iteration":689,"passed_time":0.6227350026,"remaining_time":0.2797794939},
{"learn":[3.532628335],"iteration":690,"passed_time":0.6233779346,"remaining_time":0.2787608999},
{"learn":[3.532204987],"iteration":691,"passed_time":0.6239885749,"remaining_time":0.2777290189},
{"learn":[3.530618147],"iteration":692,"passed_time":0.624611553,"remaining_time":0.2767038193},
{"learn":[3.528909306],"iteration":693,"passed_time":0.625229351,"remaining_time":0.2756774948},
{"learn":[3.526700678],"iteration":694,"passed_time":0.6258983459,"remaining_time":0.2746748137},
{"learn":[3.526439574],"iteration":695,"passed_time":0.6264948357,"remaining_time":0.2736414225},
{"learn":[3.525784216],"iteration":696,"passed_time":0.627127088,"remaining_time":0.2726248317},
{"learn":[3.524112693],"iteration":697,"passed_time":0.6277655822,"remaining_time":0.2716120427},
{"learn":[3.522813541],"iteration":698,"passed_time":0.6283995247,"remaining_time":0.2705983647},
{"learn":[3.519148203],"iteration":699,"passed_time":0.6290344092,"remaining_time":0.2695861754},
{"learn":[3.517236747],"iteration":700,"passed_time":0.6296569897,"remaining_time":0.2685698144},
{"learn":[3.515603888],"iteration":701,"passed_time":0.6303305613,"remaining_time":0.2675762212},
{"learn":[3.51263524],"iteration":702,"passed_time":0.6309738085,"remaining_time":0.266570727},
{"learn":[3.51123442],"iteration":703,"passed_time":0.6316060859,"remaining_time":0.2655616498},
{"learn":[3.50828027],"iteration":704,"passed_time":0.632258655,"remaining_time":0.2645621322},
{"learn":[3.508265537],"iteration":705,"passed_time":0.6326419581,"remaining_time":0.263451467},
{"learn":[3.506774876],"iteration":706,"passed_time":0.6332764398,"remaining_time":0.2624469545},
{"learn":[3.50552068],"iteration":707,"passed_time":0.6339170504,"remaining_time":0.2614460151},
{"learn":[3.501973993],"iteration":708,"passed_time":0.6345295155,"remaining_time":0.2604345402},
{"learn":[3.498880354],"iteration":709,"passed_time":0.6351553879,"remaining_time":0.2594296655},
{"learn":[3.497370959],"iteration":710,"passed_time":0.6357704652,"remaining_time":0.258421469},
{"learn":[3.496050455],"iteration":711,"passed_time":0.6363787615,"remaining_time":0.2574116339},
{"learn":[3.495630067],"iteration":712,"passed_time":0.6369715879,"remaining_time":0.2563966981},
{"learn":[3.49550669],"iteration":713,"passed_time":0.6376042916,"remaining_time":0.2553989179},
{"learn":[3.493652375],"iteration":714,"passed_time":0.6382443457,"remaining_time":0.2544050889},
{"learn":[3.491915684],"iteration":715,"passed_time":0.6388733712,"remaining_time":0.2534078735},
{"learn":[3.490303956],"iteration":716,"passed_time":0.6394846331,"remaining_time":0.2524046739},
{"learn":[3.488363853],"iteration":717,"passed_time":0.6401113841,"remaining_time":0.2514086495},
{"learn":[3.485483936],"iteration":718,"passed_time":0.6407953429,"remaining_time":0.2504360102},
{"learn":[3.483763466],"iteration":719,"passed_time":0.6414053633,"remaining_time":0.2494354191},
{"learn":[3.481642352],"iteration":720,"passed_time":0.6420140034,"remaining_time":0.2484353772},
{"learn":[3.479826119],"iteration":721,"passed_time":0.642640889,"remaining_time":0.2474434448},
{"learn":[3.478588728],"iteration":722,"passed_time":0.6432462337,"remaining_time":0.2464442693},
{"learn":[3.475390887],"iteration":723,"passed_time":0.6438996804,"remaining_time":0.2454645191},
{"learn":[3.472636852],"iteration":724,"passed_time":0.6445027871,"remaining_time":0.2444665744},
{"learn":[3.47061883],"iteration":725,"passed_time":0.6451348858,"remaining_time":0.2434806594},
{"learn":[3.46953149],"iteration":726,"passed_time":0.6457543089,"remaining_time":0.2424909578},
{"learn":[3.467217162],"iteration":727,"passed_time":0.6463949013,"remaining_time":0.2415101829},
{"learn":[3.465686216],"iteration":728,"passed_time":0.6470556438,"remaining_time":0.2405378319},
{"learn":[3.462631216],"iteration":729,"passed_time":0.6476699293,"remaining_time":0.2395491519},
{"learn":[3.461451053],"iteration":730,"passed_time":0.6482829014,"remaining_time":0.238561013},
{"learn":[3.458950469],"iteration":731,"passed_time":0.6489123783,"remaining_time":0.2375799418},
{"learn":[3.458072145],"iteration":732,"passed_time":0.6495559102,"remaining_time":0.2366049495},
{"learn":[3.454364268],"iteration":733,"passed_time":0.6502026671,"remaining_time":0.2356320292},
{"learn":[3.453243406],"iteration":734,"passed_time":0.6508262321,"remaining_time":0.2346516347},
{"learn":[3.453017963],"iteration":735,"passed_time":0.6515025001,"remaining_time":0.2336911142},
{"learn":[3.45201581],"iteration":736,"passed_time":0.6521634353,"remaining_time":0.2327258935},
{"learn":[3.449510107],"iteration":737,"passed_time":0.6527921917,"remaining_time":0.2317500735},
{"learn":[3.447189189],"iteration":738,"passed_time":0.6534393931,"remaining_time":0.2307817072},
{"learn":[3.446423605],"iteration":739,"passed_time":0.654120356,"remaining_time":0.229826071},
{"learn":[3.445531987],"iteration":740,"passed_time":0.6548159173,"remaining_time":0.2288762788},
{"learn":[3.445328199],"iteration":741,"passed_time":0.6555351568,"remaining_time":0.2279354049},
{"learn":[3.443327544],"iteration":742,"passed_time":0.6562384123,"remaining_time":0.2269895989},
{"learn":[3.441475798],"iteration":743,"passed_time":0.6569172665,"remaining_time":0.2260360487},
{"learn":[3.439046501],"iteration":744,"passed_time":0.6575836466,"remaining_time":0.2250789663},
{"learn":[3.435899469],"iteration":745,"passed_time":0.6582758153,"remaining_time":0.2241314438},
{"learn":[3.433988352],"iteration":746,"passed_time":0.65892576,"remaining_time":0.2231703043},
{"learn":[3.433413263],"iteration":747,"passed_time":0.6595564453,"remaining_time":0.2222035083},
{"learn":[3.429944699],"iteration":748,"passed_time":0.6601691691,"remaining_time":0.2212315907},
{"learn":[3.429291634],"iteration":749,"passed_time":0.6607945259,"remaining_time":0.220264842},
{"learn":[3.429175603],"iteration":750,"passed_time":0.6614267765,"remaining_time":0.2193012881},
{"learn":[3.428780323],"iteration":751,"passed_time":0.6620288796,"remaining_time":0.2183286731},
{"learn":[3.423893341],"iteration":752,"passed_time":0.6626521155,"remaining_time":0.2173639742},
{"learn":[3.421024316],"iteration":753,"passed_time":0.6632963037,"remaining_time":0.2164070169},
{"learn":[3.420969872],"iteration":754,"passed_time":0.6639016736,"remaining_time":0.2154382914},
{"learn":[3.419544785],"iteration":755,"passed_time":0.6645350588,"remaining_time":0.2144795692},
{"learn":[3.417057977],"iteration":756,"passed_time":0.6651651599,"remaining_time":0.2135206524},
{"learn":[3.415160245],"iteration":757,"passed_time":0.6658141254,"remaining_time":0.2125686258},
{"learn":[3.412854597],"iteration":758,"passed_time":0.6664463699,"remaining_time":0.2116120885},
{"learn":[3.410926347],"iteration":759,"passed_time":0.6670695702,"remaining_time":0.2106535485},
{"learn":[3.408963843],"iteration":760,"passed_time":0.6676972023,"remaining_time":0.2096972817},
{"learn":[3.407629634],"iteration":761,"passed_time":0.6683335834,"remaining_time":0.2087446101},
{"learn":[3.404384724],"iteration":762,"passed_time":0.6689677274,"remaining_time":0.2077920726},
{"learn":[3.403041656],"iteration":763,"passed_time":0.6696129721,"remaining_time":0.2068437977},
{"learn":[3.401101731],"iteration":764,"passed_time":0.670258123,"remaining_time":0.2058962862},
{"learn":[3.400890668],"iteration":765,"passed_time":0.6708594058,"remaining_time":0.2049361631},
{"learn":[3.399289941],"iteration":766,"passed_time":0.6714718925,"remaining_time":0.2039803794},
{"learn":[3.399202366],"iteration":767,"passed_time":0.6720717082,"remaining_time":0.2030216618},
{"learn":[3.397447845],"iteration":768,"passed_time":0.6726633669,"remaining_time":0.2020614275},
{"learn":[3.394655341],"iteration":769,"passed_time":0.6733117029,"remaining_time":0.2011190801},
{"learn":[3.393228229],"iteration":770,"passed_time":0.6739362333,"remaining_time":0.2001704247},
{"learn":[3.389691197],"iteration":771,"passed_time":0.6745610353,"remaining_time":0.1992226892},
{"learn":[3.389626772],"iteration":772,"passed_time":0.6751491017,"remaining_time":0.1982650014},
{"learn":[3.388480222],"iteration":773,"passed_time":0.6757589407,"remaining_time":0.1973146261},
{"learn":[3.388215066],"iteration":774,"passed_time":0.6763549557,"remaining_time":0.1963611162},
{"learn":[3.386324358],"iteration":775,"passed_time":0.6770072105,"remaining_time":0.1954247618},
{"learn":[3.383913061],"iteration":776,"passed_time":0.6776210064,"remaining_time":0.1944781009},
{"learn":[3.382839768],"iteration":777,"passed_time":0.6782689058,"remaining_time":0.1935420271},
{"learn":[3.381961844],"iteration":778,"passed_time":0.6789059988,"remaining_time":0.1926036274},
{"learn":[3.381521703],"iteration":779,"passed_time":0.6795276565,"remaining_time":0.1916616467},
{"learn":[3.380918963],"iteration":780,"passed_time":0.680168044,"remaining_time":0.1907257383},
{"learn":[3.377139006],"iteration":781,"passed_time":0.6808112894,"remaining_time":0.1897913825},
{"learn":[3.376004372],"iteration":782,"passed_time":0.6814451199,"remaining_time":0.1888551609},
{"learn":[3.373826468],"iteration":783,"passed_time":0.6821008967,"remaining_time":0.1879257573},
{"learn":[3.373546786],"iteration":784,"passed_time":0.6827299005,"remaining_time":0.186989718},
{"learn":[3.372109181],"iteration":785,"passed_time":0.6833529099,"remaining_time":0.1860528279},
{"learn":[3.370764924],"iteration":786,"passed_time":0.6839788057,"remaining_time":0.1851175167},
{"learn":[3.367833107],"iteration":787,"passed_time":0.6845997863,"remaining_time":0.1841816684},
{"learn":[3.36450404],"iteration":788,"passed_time":0.6852347567,"remaining_time":0.1832503595},
{"learn":[3.361794558],"iteration":789,"passed_time":0.6858550488,"remaining_time":0.182315899},
{"learn":[3.356880529],"iteration":790,"passed_time":0.6865238492,"remaining_time":0.1813950499},
{"learn":[3.353843509],"iteration":791,"passed_time":0.6871226648,"remaining_time":0.1804564574},
{"learn":[3.353640253],"iteration":792,"passed_time":0.6877229865,"remaining_time":0.179519115},
{"learn":[3.353055088],"iteration":793,"passed_time":0.6883071949,"remaining_time":0.178578441},
{"learn":[3.351415617],"iteration":794,"passed_time":0.6889175583,"remaining_time":0.1776454081},
{"learn":[3.349169061],"iteration":795,"passed_time":0.6895643656,"remaining_time":0.1767225259},
{"learn":[3.346211014],"iteration":796,"passed_time":0.6902033615,"remaining_time":0.1757983468},
{"learn":[3.344560452],"iteration":797,"passed_time":0.6908391584,"remaining_time":0.1748740727},
{"learn":[3.344445461],"iteration":798,"passed_time":0.6914345709,"remaining_time":0.1739403614},
{"learn":[3.342608898],"iteration":799,"passed_time":0.6920908104,"remaining_time":0.1730227026},
{"learn":[3.339572899],"iteration":800,"passed_time":0.6927307873,"remaining_time":0.1721016563},
{"learn":[3.339309302],"iteration":801,"passed_time":0.6933337438,"remaining_time":0.1711721712},
{"learn":[3.33698088],"iteration":802,"passed_time":0.6939603576,"remaining_time":0.1702493032},
{"learn":[3.334746342],"iteration":803,"passed_time":0.6946175433,"remaining_time":0.169334625},
{"learn":[3.332048511],"iteration":804,"passed_time":0.6955242209,"remaining_time":0.1684810225},
{"learn":[3.331932544],"iteration":805,"passed_time":0.696248176,"remaining_time":0.1675833079},
{"learn":[3.330541133],"iteration":806,"passed_time":0.6968790888,"remaining_time":0.1666637722},
{"learn":[3.329124989],"iteration":807,"passed_time":0.6975459715,"remaining_time":0.1657534982},
{"learn":[3.32583918],"iteration":808,"passed_time":0.6981759485,"remaining_time":0.1648351127},
{"learn":[3.325287299],"iteration":809,"passed_time":0.6987968865,"remaining_time":0.1639153191},
{"learn":[3.322745162],"iteration":810,"passed_time":0.6994117658,"remaining_time":0.1629948505},
{"learn":[3.319733662],"iteration":811,"passed_time":0.7000384092,"remaining_time":0.1620778583},
{"learn":[3.318080007],"iteration":812,"passed_time":0.7007070985,"remaining_time":0.1611712514},
{"learn":[3.317179538],"iteration":813,"passed_time":0.7013682325,"remaining_time":0.1602635028},
{"learn":[3.315685949],"iteration":814,"passed_time":0.7019529219,"remaining_time":0.1593390068},
{"learn":[3.314944576],"iteration":815,"passed_time":0.7025442333,"remaining_time":0.1584168369},
{"learn":[3.312369052],"iteration":816,"passed_time":0.7032252483,"remaining_time":0.1575155697},
{"learn":[3.312321621],"iteration":817,"passed_time":0.7036941982,"remaining_time":0.1565676578},
{"learn":[3.309465776],"iteration":818,"passed_time":0.7043459573,"remaining_time":0.1556613166},
{"learn":[3.308307377],"iteration":819,"passed_time":0.7049759498,"remaining_time":0.1547508183},
{"learn":[3.308076804],"iteration":820,"passed_time":0.7055639034,"remaining_time":0.1538318376},
{"learn":[3.305643326],"iteration":821,"passed_time":0.7062257076,"remaining_time":0.1529296544},
{"learn":[3.304154814],"iteration":822,"passed_time":0.7069164022,"remaining_time":0.1520342688},
{"learn":[3.303076321],"iteration":823,"passed_time":0.7075542296,"remaining_time":0.1511280879},
{"learn":[3.301746372],"iteration":824,"passed_time":0.708192834,"remaining_time":0.1502227224},
{"learn":[3.301345455],"iteration":825,"passed_time":0.7088192264,"remaining_time":0.1493154303},
{"learn":[3.299181039],"iteration":826,"passed_time":0.7094586998,"remaining_time":0.1484115539},
{"learn":[3.297989357],"iteration":827,"passed_time":0.7100905823,"remaining_time":0.1475067393},
{"learn":[3.294775182],"iteration":828,"passed_time":0.7107309038,"remaining_time":0.1466043239},
{"learn":[3.293840636],"iteration":829,"passed_time":0.71140411,"remaining_time":0.1457092755},
{"learn":[3.289279397],"iteration":830,"passed_time":0.712080635,"remaining_time":0.144815436},
{"learn":[3.286204979],"iteration":831,"passed_time":0.7127064293,"remaining_time":0.1439118751},
{"learn":[3.284833593],"iteration":832,"passed_time":0.7133602806,"remaining_time":0.1430146061},
{"learn":[3.283519914],"iteration":833,"passed_time":0.7140431386,"remaining_time":0.1421236943},
{"learn":[3.282853026],"iteration":834,"passed_time":0.7147147752,"remaining_time":0.1412310634},
{"learn":[3.281944673],"iteration":835,"passed_time":0.7153502005,"remaining_time":0.1403318575},
{"learn":[3.279764865],"iteration":836,"passed_time":0.7160009917,"remaining_time":0.1394362744},
{"learn":[3.277468839],"iteration":837,"passed_time":0.716635791,"remaining_time":0.1385381839},
{"learn":[3.277124974],"iteration":838,"passed_time":0.7173023309,"remaining_time":0.137646812},
{"learn":[3.275636037],"iteration":839,"passed_time":0.7179407825,"remaining_time":0.1367506252},
{"learn":[3.274413635],"iteration":840,"passed_time":0.7185772,"remaining_time":0.1358546668},
{"learn":[3.272636087],"iteration":841,"passed_time":0.7192220028,"remaining_time":0.1349608984},
{"learn":[3.269644466],"iteration":842,"passed_time":0.7199347426,"remaining_time":0.1340803732},
{"learn":[3.26852083],"iteration":843,"passed_time":0.7205971241,"remaining_time":0.1331909376},
{"learn":[3.267820927],"iteration":844,"passed_time":0.7212368831,"remaining_time":0.1322978898},
{"learn":[3.267331099],"iteration":845,"passed_time":0.7218637374,"remaining_time":0.1314030917},
{"learn":[3.267231014],"iteration":846,"passed_time":0.7224620217,"remaining_time":0.1305037654},
{"learn":[3.267158695],"iteration":847,"passed_time":0.7230544521,"remaining_time":0.1296040999},
{"learn":[3.264718705],"iteration":848,"passed_time":0.723663456,"remaining_time":0.1287081058},
{"learn":[3.261678512],"iteration":849,"passed_time":0.7243275625,"remaining_time":0.127822511},
{"learn":[3.261368381],"iteration":850,"passed_time":0.7249625945,"remaining_time":0.1269323462},
{"learn":[3.260128799],"iteration":851,"passed_time":0.7255678863,"remaining_time":0.126037614},
{"learn":[3.258972952],"iteration":852,"passed_time":0.7261650446,"remaining_time":0.1251421589},
{"learn":[3.258724846],"iteration":853,"passed_time":0.7268160744,"remaining_time":0.1242566123},
{"learn":[3.25686724],"iteration":854,"passed_time":0.727484058,"remaining_time":0.1233744894},
{"learn":[3.255750259],"iteration":855,"passed_time":0.7280969059,"remaining_time":0.1224835916},
{"learn":[3.254915866],"iteration":856,"passed_time":0.7287348496,"remaining_time":0.1215975303},
{"learn":[3.254348625],"iteration":857,"passed_time":0.7293802792,"remaining_time":0.1207132863},
{"learn":[3.253408514],"iteration":858,"passed_time":0.7300215488,"remaining_time":0.1198289155},
{"learn":[3.253291714],"iteration":859,"passed_time":0.7306104902,"remaining_time":0.1189365914},
{"learn":[3.250186342],"iteration":860,"passed_time":0.7312729325,"remaining_time":0.1180568381},
{"learn":[3.249141318],"iteration":861,"passed_time":0.7319622763,"remaining_time":0.1171818957},
{"learn":[3.246300388],"iteration":862,"passed_time":0.7326096288,"remaining_time":0.1163007174},
{"learn":[3.245205135],"iteration":863,"passed_time":0.733243725,"remaining_time":0.1154179937},
{"learn":[3.244403535],"iteration":864,"passed_time":0.7339027026,"remaining_time":0.1145397281},
{"learn":[3.244211781],"iteration":865,"passed_time":0.7345072972,"remaining_time":0.1136535541},
{"learn":[3.242286347],"iteration":866,"passed_time":0.7351200332,"remaining_time":0.1127692784},
{"learn":[3.239606746],"iteration":867,"passed_time":0.735746252,"remaining_time":0.1118876789},
{"learn":[3.236773361],"iteration":868,"passed_time":0.7363583039,"remaining_time":0.1110045314},
{"learn":[3.234552446],"iteration":869,"passed_time":0.7370135541,"remaining_time":0.1101284621},
{"learn":[3.233724647],"iteration":870,"passed_time":0.7376515743,"remaining_time":0.109250348},
{"learn":[3.230851485],"iteration":871,"passed_time":0.7383185143,"remaining_time":0.1083770296},
{"learn":[3.227728941],"iteration":872,"passed_time":0.7389397457,"remaining_time":0.1074975346},
{"learn":[3.225787575],"iteration":873,"passed_time":0.7396153896,"remaining_time":0.1066264749},
{"learn":[3.222797487],"iteration":874,"passed_time":0.7402460376,"remaining_time":0.1057494339},
{"learn":[3.22137014],"iteration":875,"passed_time":0.7408637123,"remaining_time":0.1048711191},
{"learn":[3.219701963],"iteration":876,"passed_time":0.7415000691,"remaining_time":0.1039960188},
{"learn":[3.21783327],"iteration":877,"passed_time":0.7421947528,"remaining_time":0.103129567},
{"learn":[3.217713355],"iteration":878,"passed_time":0.7428180365,"remaining_time":0.1022536774},
{"learn":[3.217666091],"iteration":879,"passed_time":0.7433942564,"remaining_time":0.1013719441},
{"learn":[3.214962005],"iteration":880,"passed_time":0.7440610237,"remaining_time":0.1005031349},
{"learn":[3.214081828],"iteration":881,"passed_time":0.7446912393,"remaining_time":0.0996298937},
{"learn":[3.213358337],"iteration":882,"passed_time":0.7453003066,"remaining_time":0.09875440076},
{"learn":[3.210850401],"iteration":883,"passed_time":0.745952472,"remaining_time":0.09788516601},
{"learn":[3.207810328],"iteration":884,"passed_time":0.7465758598,"remaining_time":0.09701268235},
{"learn":[3.204935073],"iteration":885,"passed_time":0.7471962987,"remaining_time":0.09614038154},
{"learn":[3.20280198],"iteration":886,"passed_time":0.747840578,"remaining_time":0.09527168581},
{"learn":[3.200663495],"iteration":887,"passed_time":0.7484673081,"remaining_time":0.09440128211},
{"learn":[3.197301669],"iteration":888,"passed_time":0.7491151529,"remaining_time":0.09353406296},
{"learn":[3.195666943],"iteration":889,"passed_time":0.7497608559,"remaining_time":0.09266707208},
{"learn":[3.193886506],"iteration":890,"passed_time":0.7503922314,"remaining_time":0.09179882517},
{"learn":[3.190601248],"iteration":891,"passed_time":0.7510209357,"remaining_time":0.09093078593},
{"learn":[3.188983797],"iteration":892,"passed_time":0.7516485027,"remaining_time":0.09006314646},
{"learn":[3.187365749],"iteration":893,"passed_time":0.75226986,"remaining_time":0.08919530779},
{"learn":[3.186160771],"iteration":894,"passed_time":0.7529350182,"remaining_time":0.08833315856},
{"learn":[3.185358981],"iteration":895,"passed_time":0.753562745,"remaining_time":0.08746710433},
{"learn":[3.183832164],"iteration":896,"passed_time":0.7542032584,"remaining_time":0.08660304974},
{"learn":[3.183106966],"iteration":897,"passed_time":0.7548491572,"remaining_time":0.08574010471},
{"learn":[3.182838152],"iteration":898,"passed_time":0.7554509287,"remaining_time":0.08487268498},
{"learn":[3.180835453],"iteration":899,"passed_time":0.7561499621,"remaining_time":0.08401666245},
{"learn":[3.179957348],"iteration":900,"passed_time":0.7568180107,"remaining_time":0.08315758386},
{"learn":[3.179752966],"iteration":901,"passed_time":0.7574329222,"remaining_time":0.08229315563},
{"learn":[3.178851983],"iteration":902,"passed_time":0.7580922288,"remaining_time":0.08143404894},
{"learn":[3.176748586],"iteration":903,"passed_time":0.7587076169,"remaining_time":0.08057072037},
{"learn":[3.172960988],"iteration":904,"passed_time":0.7593940854,"remaining_time":0.07971540123},
{"learn":[3.172794225],"iteration":905,"passed_time":0.7599847753,"remaining_time":0.07885051752},
{"learn":[3.169996507],"iteration":906,"passed_time":0.7606185563,"remaining_time":0.07799065683},
{"learn":[3.16813015],"iteration":907,"passed_time":0.7612503381,"remaining_time":0.07713109153},
{"learn":[3.166920871],"iteration":908,"passed_time":0.7619509424,"remaining_time":0.07627891722},
{"learn":[3.16531606],"iteration":909,"passed_time":0.7626179458,"remaining_time":0.07542375288},
{"learn":[3.162035247],"iteration":910,"passed_time":0.7632714516,"remaining_time":0.07456768297},
{"learn":[3.16189467],"iteration":911,"passed_time":0.7638878953,"remaining_time":0.07370848112},
{"learn":[3.161008416],"iteration":912,"passed_time":0.7645479624,"remaining_time":0.07285396794},
{"learn":[3.160560787],"iteration":913,"passed_time":0.7651476651,"remaining_time":0.07199420044},
{"learn":[3.160416261],"iteration":914,"passed_time":0.7657380833,"remaining_time":0.07113413888},
{"learn":[3.15844291],"iteration":915,"passed_time":0.7663978144,"remaining_time":0.07028102228},
{"learn":[3.155040501],"iteration":916,"passed_time":0.7670201805,"remaining_time":0.06942494545},
{"learn":[3.154937548],"iteration":917,"passed_time":0.7676036796,"remaining_time":0.06856590602},
{"learn":[3.153721161],"iteration":918,"passed_time":0.7682426408,"remaining_time":0.06771235463},
{"learn":[3.153170511],"iteration":919,"passed_time":0.7688565019,"remaining_time":0.06685708712},
{"learn":[3.153113601],"iteration":920,"passed_time":0.7695037823,"remaining_time":0.06600521042},
{"learn":[3.150607379],"iteration":921,"passed_time":0.7701595209,"remaining_time":0.06515449309},
{"learn":[3.148408359],"iteration":922,"passed_time":0.7707914615,"remaining_time":0.06430221293},
{"learn":[3.147495728],"iteration":923,"passed_time":0.7714045265,"remaining_time":0.06344885716},
{"learn":[3.146946235],"iteration":924,"passed_time":0.7720646509,"remaining_time":0.06259983656},
{"learn":[3.14472738],"iteration":925,"passed_time":0.7726892819,"remaining_time":0.06174838754},
{"learn":[3.144469477],"iteration":926,"passed_time":0.7732861815,"remaining_time":0.06089524406},
{"learn":[3.142975516],"iteration":927,"passed_time":0.7739085901,"remaining_time":0.06004463199},
{"learn":[3.14079113],"iteration":928,"passed_time":0.7745230267,"remaining_time":0.05919390193},
{"learn":[3.138173032],"iteration":929,"passed_time":0.7751518968,"remaining_time":0.05834476642},
{"learn":[3.136352813],"iteration":930,"passed_time":0.7757775296,"remaining_time":0.05749586417},
{"learn":[3.133735004],"iteration":931,"passed_time":0.7764475619,"remaining_time":0.05665068048},
{"learn":[3.1319496],"iteration":932,"passed_time":0.7771342058,"remaining_time":0.05580706516},
{"learn":[3.129865343],"iteration":933,"passed_time":0.7777919385,"remaining_time":0.05496174298},
{"learn":[3.129830206],"iteration":934,"passed_time":0.7782606809,"remaining_time":0.0541036837},
{"learn":[3.126676562],"iteration":935,"passed_time":0.7789191515,"remaining_time":0.05325942916},
{"learn":[3.12645665],"iteration":936,"passed_time":0.7795617605,"remaining_time":0.05241450471},
{"learn":[3.126378007],"iteration":937,"passed_time":0.7801496594,"remaining_time":0.0515663954},
{"learn":[3.124621914],"iteration":938,"passed_time":0.780757546,"remaining_time":0.05072013877},
{"learn":[3.123379018],"iteration":939,"passed_time":0.7813835564,"remaining_time":0.04987554616},
{"learn":[3.123332451],"iteration":940,"passed_time":0.7819816931,"remaining_time":0.04902967045},
{"learn":[3.122432444],"iteration":941,"passed_time":0.7826008037,"remaining_time":0.04818561212},
{"learn":[3.121889006],"iteration":942,"passed_time":0.783390562,"remaining_time":0.04735234574},
{"learn":[3.121070914],"iteration":943,"passed_time":0.7841756158,"remaining_time":0.04651889246},
{"learn":[3.118444705],"iteration":944,"passed_time":0.7848649614,"remaining_time":0.0456799713},
{"learn":[3.116820458],"iteration":945,"passed_time":0.7855180157,"remaining_time":0.04483929477},
{"learn":[3.114971041],"iteration":946,"passed_time":0.7861662424,"remaining_time":0.0439987443},
{"learn":[3.114685138],"iteration":947,"passed_time":0.7868054059,"remaining_time":0.04315810243},
{"learn":[3.113399363],"iteration":948,"passed_time":0.787467981,"remaining_time":0.04231914334},
{"learn":[3.110575399],"iteration":949,"passed_time":0.7880856809,"remaining_time":0.04147819373},
{"learn":[3.110466553],"iteration":950,"passed_time":0.7887300739,"remaining_time":0.04063908898},
{"learn":[3.108691641],"iteration":951,"passed_time":0.7894252897,"remaining_time":0.03980295578},
{"learn":[3.107898017],"iteration":952,"passed_time":0.7900696558,"remaining_time":0.03896461052},
{"learn":[3.105551729],"iteration":953,"passed_time":0.7907521744,"remaining_time":0.03812851155},
{"learn":[3.104824945],"iteration":954,"passed_time":0.7913414926,"remaining_time":0.03728834259},
{"learn":[3.103186704],"iteration":955,"passed_time":0.7920052501,"remaining_time":0.03645212448},
{"learn":[3.102330655],"iteration":956,"passed_time":0.7926901126,"remaining_time":0.03561721509},
{"learn":[3.102291298],"iteration":957,"passed_time":0.7933469624,"remaining_time":0.03478139084},
{"learn":[3.100363529],"iteration":958,"passed_time":0.7939349785,"remaining_time":0.03394299699},
{"learn":[3.097871596],"iteration":959,"passed_time":0.7946186178,"remaining_time":0.03310910908},
{"learn":[3.097372213],"iteration":960,"passed_time":0.7952863088,"remaining_time":0.03227488662},
{"learn":[3.095981813],"iteration":961,"passed_time":0.796081393,"remaining_time":0.03144604255},
{"learn":[3.095347452],"iteration":962,"passed_time":0.796731744,"remaining_time":0.03061170771},
{"learn":[3.094728409],"iteration":963,"passed_time":0.7973881771,"remaining_time":0.02977798172},
{"learn":[3.094118537],"iteration":964,"passed_time":0.798033664,"remaining_time":0.02894422615},
{"learn":[3.093793695],"iteration":965,"passed_time":0.7987065203,"remaining_time":0.0281118237},
{"learn":[3.092581602],"iteration":966,"passed_time":0.7993764389,"remaining_time":0.02727965097},
{"learn":[3.091694202],"iteration":967,"passed_time":0.7999952144,"remaining_time":0.02644612279},
{"learn":[3.090298312],"iteration":968,"passed_time":0.8006416059,"remaining_time":0.02561392134},
{"learn":[3.090020107],"iteration":969,"passed_time":0.8013034431,"remaining_time":0.02478258071},
{"learn":[3.088949869],"iteration":970,"passed_time":0.8019431639,"remaining_time":0.02395092868},
{"learn":[3.086700204],"iteration":971,"passed_time":0.8026054846,"remaining_time":0.0231203226},
{"learn":[3.086584317],"iteration":972,"passed_time":0.8032627641,"remaining_time":0.02228992254},
{"learn":[3.084850742],"iteration":973,"passed_time":0.8039063507,"remaining_time":0.02145951244},
{"learn":[3.084239948],"iteration":974,"passed_time":0.804510493,"remaining_time":0.02062847418},
{"learn":[3.082561673],"iteration":975,"passed_time":0.8051947756,"remaining_time":0.01979987153},
{"learn":[3.07991814],"iteration":976,"passed_time":0.8058191627,"remaining_time":0.01897015429},
{"learn":[3.079350277],"iteration":977,"passed_time":0.806452126,"remaining_time":0.01814104987},
{"learn":[3.077637462],"iteration":978,"passed_time":0.8070918511,"remaining_time":0.01731249119},
{"learn":[3.076733301],"iteration":979,"passed_time":0.8077216223,"remaining_time":0.01648411474},
{"learn":[3.07594065],"iteration":980,"passed_time":0.8083358341,"remaining_time":0.01565584184},
{"learn":[3.072594655],"iteration":981,"passed_time":0.8089582887,"remaining_time":0.01482815601},
{"learn":[3.071977674],"iteration":982,"passed_time":0.8096093377,"remaining_time":0.01400138224},
{"learn":[3.069532634],"iteration":983,"passed_time":0.8102411898,"remaining_time":0.01317465349},
{"learn":[3.068870784],"iteration":984,"passed_time":0.8108984051,"remaining_time":0.01234870668},
{"learn":[3.068801463],"iteration":985,"passed_time":0.8114855296,"remaining_time":0.01152210691},
{"learn":[3.067433249],"iteration":986,"passed_time":0.8121464969,"remaining_time":0.010696965},
{"learn":[3.065611456],"iteration":987,"passed_time":0.8127918319,"remaining_time":0.009871965569},
{"learn":[3.063039162],"iteration":988,"passed_time":0.8134031849,"remaining_time":0.0090469515},
{"learn":[3.06177873],"iteration":989,"passed_time":0.814036498,"remaining_time":0.008222590889},
{"learn":[3.061689148],"iteration":990,"passed_time":0.8146314287,"remaining_time":0.007398267264},
{"learn":[3.058984039],"iteration":991,"passed_time":0.8152564538,"remaining_time":0.006574648821},
{"learn":[3.057492984],"iteration":992,"passed_time":0.8158706231,"remaining_time":0.005751353838},
{"learn":[3.057290731],"iteration":993,"passed_time":0.8165112754,"remaining_time":0.004928639489},
{"learn":[3.056068348],"iteration":994,"passed_time":0.8171286332,"remaining_time":0.004106174036},
{"learn":[3.054987307],"iteration":995,"passed_time":0.817771626,"remaining_time":0.003284223397},
{"learn":[3.054200234],"iteration":996,"passed_time":0.8184048506,"remaining_time":0.002462602359},
{"learn":[3.052732869],"iteration":997,"passed_time":0.8190434046,"remaining_time":0.001641369548},
{"learn":[3.051787862],"iteration":998,"passed_time":0.8196660832,"remaining_time":0.0008204865698},
{"learn":[3.051366222],"iteration":999,"passed_time":0.8202996299,"remaining_time":0}
]}